Workbook

Sheet Outputs-R
B3: Dashboard: Perpetuity Method
D6: Model Drivers Set To | F6: =Outputs!F6 -> 2 | L6: All figures in USD thousands unless stated
D9: Main Outputs 1 | L9: Selected Inputs
W10: Learner | X10: Correct | Y10: Compare
F11: Enterprise | G11: Equity | H11: Equity | W11: =Outputs!F13 -> 125713.01 | X11: =F13 -> 125713.01 | Y11: =IF(W11=0,0,IF(W11=X11,1,0)) -> 1
F12: Value | G12: Value | H12: Per Share | L12: Terminal Growth Rate | O12: ='Inputs-R'!F107 -> 0.02
F13: =Model!H488 -> 125713.01 | L13: WACC | O13: ='Inputs-R'!L84 -> 0.095866057 | S13: Learner | T13: Correct | U13: Compare | W13: Learner | X13: Correct | Y13: Compare | AA13: Learner | AB13: Correct | AC13: Compare | AE13: Learner | AF13: Correct | AG13: Compare
D14: Best Case | E14: 1 | F14: 125713.01 | G14: =Outputs!F14-$O$14 -> 157873.71 | H14: =Outputs!G14/$O$15 -> 4.6161905 | L14: Net Debt | N14: =CONCATENATE("(End of ",'Model-R'!$H$5,")") -> (End of 2022) | O14: ='Inputs-R'!L94 -> 18642 | S14: =SUM(Outputs!E14:E16) -> 6 | T14: =SUM(E14:E16) -> 6 | U14: =IF(S14=0,0,IF(S14=T14,1,0)) -> 1 | W14: =IFERROR(_xlfn.FORMULATEXT(Outputs!F14),0) -> 0 | X14: =IFERROR(_xlfn.FORMULATEXT(F14),0) -> 0 | Y14: =IF(W14=0,0,IF(W14=X14,1,0)) -> 0 | AA14: =SUM(Outputs!G14:G16) -> 333266.66 | AB14: =SUM(G14:G16) -> 333266.66 | AC14: =IF(AA14=0,0,IF(AA14=AB14,1,0)) -> 1 | AE14: =SUM(Outputs!H14:H16) -> 9.7446393 | AF14: =SUM(H14:H16) -> 9.7446393 | AG14: =IF(AE14=0,0,IF(AE14=AF14,1,0)) -> 1
D15: Base Case | E15: 2 | F15: 125713.01 | G15: =Outputs!F15-$O$14 -> 107071.01 | H15: =Outputs!G15/$O$15 -> 3.1307312 | L15: Shares Outstanding | N15: (FD 000) | O15: ='Inputs-R'!F105 -> 34200 | W15: =IFERROR(_xlfn.FORMULATEXT(Outputs!F15),0) -> 0 | X15: =IFERROR(_xlfn.FORMULATEXT(F15),0) -> 0 | Y15: =IF(W15=0,0,IF(W15=X15,1,0)) -> 0
D16: Worst Case | E16: 3 | F16: 125713.01 | G16: =Outputs!F16-$O$14 -> 68321.94 | H16: =Outputs!G16/$O$15 -> 1.9977176 | L16: Current Stock Price | N16: (US$/sh) | O16: ='Inputs-R'!F106 -> 2.23 | W16: =IFERROR(_xlfn.FORMULATEXT(Outputs!F16),0) -> 0 | X16: =IFERROR(_xlfn.FORMULATEXT(F16),0) -> 0 | Y16: =IF(W16=0,0,IF(W16=X16,1,0)) -> 0
U18: =U14 -> 1 | Y18: =IF(SUM(Y14:Y16)=3,1,0) -> 0 | AC18: =AC14 -> 1 | AG18: =AG14 -> 1
D20: Enterprise Value 1 | L20: Equity Value per Share | S20: Learner | T20: Correct | U20: Compare
S21: =Outputs!C23 -> 125713.01 | T21: =C23 -> 125713.01 | U21: =IF(S21=0,0,IF(S21=T21,1,0)) -> 1
D22: Terminal Growth Rate | L22: Terminal Growth Rate
C23: ='Model-R'!H399 -> 125713.01 | D23: =E23-0.005 -> 0.01 | E23: =F23-0.005 -> 0.015 | F23: ='Inputs-R'!$F$107 -> 0.02 | G23: =F23+0.005 -> 0.025 | H23: =G23+0.005 -> 0.03 | L23: =D23 -> 0.01 | M23: =E23 -> 0.015 | N23: =F23 -> 0.02 | O23: =G23 -> 0.025 | P23: =H23 -> 0.03 | S23: Learner | Y23: Correct | AE23: Compare
B24: WACC | C24: =C25-0.01 -> 0.075866057 | D24: 125713.01 | E24: 125713.01 | F24: 125713.01 | G24: 125713.01 | H24: 125713.01 | J24: WACC | K24: =C24 -> 0.075866057 | L24: =Outputs!D37/$O$15 -> 3.1307312 | M24: =Outputs!E37/$O$15 -> 3.1307312 | N24: =Outputs!F37/$O$15 -> 3.1307312 | O24: =Outputs!G37/$O$15 -> 3.1307312 | P24: =Outputs!H37/$O$15 -> 3.1307312 | S24: =IFERROR(_xlfn.FORMULATEXT(Outputs!D24),0) -> 0 | T24: =IFERROR(_xlfn.FORMULATEXT(Outputs!E24),0) -> 0 | U24: =IFERROR(_xlfn.FORMULATEXT(Outputs!F24),0) -> 0 | V24: =IFERROR(_xlfn.FORMULATEXT(Outputs!G24),0) -> 0 | W24: =IFERROR(_xlfn.FORMULATEXT(Outputs!H24),0) -> 0 | Y24: =IFERROR(_xlfn.FORMULATEXT(D24),0) -> 0 | Z24: =IFERROR(_xlfn.FORMULATEXT(E24),0) -> 0 | AA24: =IFERROR(_xlfn.FORMULATEXT(F24),0) -> 0 | AB24: =IFERROR(_xlfn.FORMULATEXT(G24),0) -> 0 | AC24: =IFERROR(_xlfn.FORMULATEXT(H24),0) -> 0 | AE24: =IF(S24=Y24,1,0) -> 1 | AF24: =IF(T24=Z24,1,0) -> 1 | AG24: =IF(U24=AA24,1,0) -> 1 | AH24: =IF(V24=AB24,1,0) -> 1 | AI24: =IF(W24=AC24,1,0) -> 1
C25: =C26-0.01 -> 0.085866057 | D25: 125713.01 | E25: 125713.01 | F25: 125713.01 | G25: 125713.01 | H25: 125713.01 | K25: =C25 -> 0.085866057 | L25: =Outputs!D38/$O$15 -> 3.1307312 | M25: =Outputs!E38/$O$15 -> 3.1307312 | N25: =Outputs!F38/$O$15 -> 3.1307312 | O25: =Outputs!G38/$O$15 -> 3.1307312 | P25: =Outputs!H38/$O$15 -> 3.1307312 | S25: =IFERROR(_xlfn.FORMULATEXT(Outputs!D25),0) -> 0 | T25: =IFERROR(_xlfn.FORMULATEXT(Outputs!E25),0) -> 0 | U25: =IFERROR(_xlfn.FORMULATEXT(Outputs!F25),0) -> 0 | V25: =IFERROR(_xlfn.FORMULATEXT(Outputs!G25),0) -> 0 | W25: =IFERROR(_xlfn.FORMULATEXT(Outputs!H25),0) -> 0 | Y25: =IFERROR(_xlfn.FORMULATEXT(D25),0) -> 0 | Z25: =IFERROR(_xlfn.FORMULATEXT(E25),0) -> 0 | AA25: =IFERROR(_xlfn.FORMULATEXT(F25),0) -> 0 | AB25: =IFERROR(_xlfn.FORMULATEXT(G25),0) -> 0 | AC25: =IFERROR(_xlfn.FORMULATEXT(H25),0) -> 0 | AE25: =IF(S25=Y25,1,0) -> 1 | AF25: =IF(T25=Z25,1,0) -> 1 | AG25: =IF(U25=AA25,1,0) -> 1 | AH25: =IF(V25=AB25,1,0) -> 1 | AI25: =IF(W25=AC25,1,0) -> 1
C26: ='Inputs-R'!$L$84 -> 0.095866057 | D26: 125713.01 | E26: 125713.01 | F26: 125713.01 | G26: 125713.01 | H26: 125713.01 | K26: =C26 -> 0.095866057 | L26: =Outputs!D39/$O$15 -> 3.1307312 | M26: =Outputs!E39/$O$15 -> 3.1307312 | N26: =Outputs!F39/$O$15 -> 3.1307312 | O26: =Outputs!G39/$O$15 -> 3.1307312 | P26: =Outputs!H39/$O$15 -> 3.1307312 | S26: =IFERROR(_xlfn.FORMULATEXT(Outputs!D26),0) -> 0 | T26: =IFERROR(_xlfn.FORMULATEXT(Outputs!E26),0) -> 0 | U26: =IFERROR(_xlfn.FORMULATEXT(Outputs!F26),0) -> 0 | V26: =IFERROR(_xlfn.FORMULATEXT(Outputs!G26),0) -> 0 | W26: =IFERROR(_xlfn.FORMULATEXT(Outputs!H26),0) -> 0 | Y26: =IFERROR(_xlfn.FORMULATEXT(D26),0) -> 0 | Z26: =IFERROR(_xlfn.FORMULATEXT(E26),0) -> 0 | AA26: =IFERROR(_xlfn.FORMULATEXT(F26),0) -> 0 | AB26: =IFERROR(_xlfn.FORMULATEXT(G26),0) -> 0 | AC26: =IFERROR(_xlfn.FORMULATEXT(H26),0) -> 0 | AE26: =IF(S26=Y26,1,0) -> 1 | AF26: =IF(T26=Z26,1,0) -> 1 | AG26: =IF(U26=AA26,1,0) -> 1 | AH26: =IF(V26=AB26,1,0) -> 1 | AI26: =IF(W26=AC26,1,0) -> 1
C27: =C26+0.01 -> 0.10586606 | D27: 125713.01 | E27: 125713.01 | F27: 125713.01 | G27: 125713.01 | H27: 125713.01 | K27: =C27 -> 0.10586606 | L27: =Outputs!D40/$O$15 -> 3.1307312 | M27: =Outputs!E40/$O$15 -> 3.1307312 | N27: =Outputs!F40/$O$15 -> 3.1307312 | O27: =Outputs!G40/$O$15 -> 3.1307312 | P27: =Outputs!H40/$O$15 -> 3.1307312 | S27: =IFERROR(_xlfn.FORMULATEXT(Outputs!D27),0) -> 0 | T27: =IFERROR(_xlfn.FORMULATEXT(Outputs!E27),0) -> 0 | U27: =IFERROR(_xlfn.FORMULATEXT(Outputs!F27),0) -> 0 | V27: =IFERROR(_xlfn.FORMULATEXT(Outputs!G27),0) -> 0 | W27: =IFERROR(_xlfn.FORMULATEXT(Outputs!H27),0) -> 0 | Y27: =IFERROR(_xlfn.FORMULATEXT(D27),0) -> 0 | Z27: =IFERROR(_xlfn.FORMULATEXT(E27),0) -> 0 | AA27: =IFERROR(_xlfn.FORMULATEXT(F27),0) -> 0 | AB27: =IFERROR(_xlfn.FORMULATEXT(G27),0) -> 0 | AC27: =IFERROR(_xlfn.FORMULATEXT(H27),0) -> 0 | AE27: =IF(S27=Y27,1,0) -> 1 | AF27: =IF(T27=Z27,1,0) -> 1 | AG27: =IF(U27=AA27,1,0) -> 1 | AH27: =IF(V27=AB27,1,0) -> 1 | AI27: =IF(W27=AC27,1,0) -> 1
C28: =C27+0.01 -> 0.11586606 | D28: 125713.01 | E28: 125713.01 | F28: 125713.01 | G28: 125713.01 | H28: 125713.01 | K28: =C28 -> 0.11586606 | L28: =Outputs!D41/$O$15 -> 3.1307312 | M28: =Outputs!E41/$O$15 -> 3.1307312 | N28: =Outputs!F41/$O$15 -> 3.1307312 | O28: =Outputs!G41/$O$15 -> 3.1307312 | P28: =Outputs!H41/$O$15 -> 3.1307312 | S28: =IFERROR(_xlfn.FORMULATEXT(Outputs!D28),0) -> 0 | T28: =IFERROR(_xlfn.FORMULATEXT(Outputs!E28),0) -> 0 | U28: =IFERROR(_xlfn.FORMULATEXT(Outputs!F28),0) -> 0 | V28: =IFERROR(_xlfn.FORMULATEXT(Outputs!G28),0) -> 0 | W28: =IFERROR(_xlfn.FORMULATEXT(Outputs!H28),0) -> 0 | Y28: =IFERROR(_xlfn.FORMULATEXT(D28),0) -> 0 | Z28: =IFERROR(_xlfn.FORMULATEXT(E28),0) -> 0 | AA28: =IFERROR(_xlfn.FORMULATEXT(F28),0) -> 0 | AB28: =IFERROR(_xlfn.FORMULATEXT(G28),0) -> 0 | AC28: =IFERROR(_xlfn.FORMULATEXT(H28),0) -> 0 | AE28: =IF(S28=Y28,1,0) -> 1 | AF28: =IF(T28=Z28,1,0) -> 1 | AG28: =IF(U28=AA28,1,0) -> 1 | AH28: =IF(V28=AB28,1,0) -> 1 | AI28: =IF(W28=AC28,1,0) -> 1
AE30: =IF(SUM(AE24:AI28)=25,1,0) -> 1
D33: Equity Value | L33: Premium (Discount) to Stock Price
D35: Terminal Growth Rate | L35: Terminal Growth Rate
D36: =D23 -> 0.01 | E36: =E23 -> 0.015 | F36: =F23 -> 0.02 | G36: =G23 -> 0.025 | H36: =H23 -> 0.03 | L36: =D36 -> 0.01 | M36: =E36 -> 0.015 | N36: =F36 -> 0.02 | O36: =G36 -> 0.025 | P36: =H36 -> 0.03 | W36: Learner | X36: Correct | Y36: Compare
B37: WACC | C37: =C24 -> 0.075866057 | D37: =Outputs!D24-$O$14 -> 107071.01 | E37: =Outputs!E24-$O$14 -> 107071.01 | F37: =Outputs!F24-$O$14 -> 107071.01 | G37: =Outputs!G24-$O$14 -> 107071.01 | H37: =Outputs!H24-$O$14 -> 107071.01 | J37: WACC | K37: =C37 -> 0.075866057 | L37: =Outputs!L24/$O$16-1 -> 0.40391535 | M37: =Outputs!M24/$O$16-1 -> 0.40391535 | N37: =Outputs!N24/$O$16-1 -> 0.40391535 | O37: =Outputs!O24/$O$16-1 -> 0.40391535 | P37: =Outputs!P24/$O$16-1 -> 0.40391535 | W37: =SUM(Outputs!L24:P28) -> 78.268281 | X37: =SUM(L24:P28) -> 78.268281 | Y37: =IF(W37=0,0,IF(W37=X37,1,0)) -> 1
C38: =C25 -> 0.085866057 | D38: =Outputs!D25-$O$14 -> 107071.01 | E38: =Outputs!E25-$O$14 -> 107071.01 | F38: =Outputs!F25-$O$14 -> 107071.01 | G38: =Outputs!G25-$O$14 -> 107071.01 | H38: =Outputs!H25-$O$14 -> 107071.01 | K38: =C38 -> 0.085866057 | L38: =Outputs!L25/$O$16-1 -> 0.40391535 | M38: =Outputs!M25/$O$16-1 -> 0.40391535 | N38: =Outputs!N25/$O$16-1 -> 0.40391535 | O38: =Outputs!O25/$O$16-1 -> 0.40391535 | P38: =Outputs!P25/$O$16-1 -> 0.40391535
C39: =C26 -> 0.095866057 | D39: =Outputs!D26-$O$14 -> 107071.01 | E39: =Outputs!E26-$O$14 -> 107071.01 | F39: =Outputs!F26-$O$14 -> 107071.01 | G39: =Outputs!G26-$O$14 -> 107071.01 | H39: =Outputs!H26-$O$14 -> 107071.01 | K39: =C39 -> 0.095866057 | L39: =Outputs!L26/$O$16-1 -> 0.40391535 | M39: =Outputs!M26/$O$16-1 -> 0.40391535 | N39: =Outputs!N26/$O$16-1 -> 0.40391535 | O39: =Outputs!O26/$O$16-1 -> 0.40391535 | P39: =Outputs!P26/$O$16-1 -> 0.40391535 | S39: Learner | T39: Correct | U39: Compare | W39: Learner | X39: Correct | Y39: Compare
C40: =C27 -> 0.10586606 | D40: =Outputs!D27-$O$14 -> 107071.01 | E40: =Outputs!E27-$O$14 -> 107071.01 | F40: =Outputs!F27-$O$14 -> 107071.01 | G40: =Outputs!G27-$O$14 -> 107071.01 | H40: =Outputs!H27-$O$14 -> 107071.01 | K40: =C40 -> 0.10586606 | L40: =Outputs!L27/$O$16-1 -> 0.40391535 | M40: =Outputs!M27/$O$16-1 -> 0.40391535 | N40: =Outputs!N27/$O$16-1 -> 0.40391535 | O40: =Outputs!O27/$O$16-1 -> 0.40391535 | P40: =Outputs!P27/$O$16-1 -> 0.40391535 | S40: =SUM(Outputs!D37:H41) -> 2676775.2 | T40: =SUM(D37:H41) -> 2676775.2 | U40: =IF(S40=0,0,IF(S40=T40,1,0)) -> 1 | W40: =SUM(Outputs!L37:P41) -> 10.097884 | X40: =SUM(L37:P41) -> 10.097884 | Y40: =IF(W40=0,0,IF(W40=X40,1,0)) -> 1
C41: =C28 -> 0.11586606 | D41: =Outputs!D28-$O$14 -> 107071.01 | E41: =Outputs!E28-$O$14 -> 107071.01 | F41: =Outputs!F28-$O$14 -> 107071.01 | G41: =Outputs!G28-$O$14 -> 107071.01 | H41: =Outputs!H28-$O$14 -> 107071.01 | K41: =C41 -> 0.11586606 | L41: =Outputs!L28/$O$16-1 -> 0.40391535 | M41: =Outputs!M28/$O$16-1 -> 0.40391535 | N41: =Outputs!N28/$O$16-1 -> 0.40391535 | O41: =Outputs!O28/$O$16-1 -> 0.40391535 | P41: =Outputs!P28/$O$16-1 -> 0.40391535
P43: These tables require the workbook calculation to be set to automatic to update. | S43: =IF(SUM(U18+U21+Y11+Y18+AC18+AG18+AE30+U40+Y37+Y40)=10,"COMPLETE","")
B47: Dashboard: Multiple Method
D50: Model Drivers Set To | L50: All figures in USD thousands unless stated
D53: Main Outputs 1 | L53: Selected Inputs
W54: Learner | X54: Correct | Y54: Compare
F55: Enterprise | G55: Equity | H55: Equity | W55: =Outputs!F57 -> 130862.76 | X55: =F57 -> 130862.76 | Y55: =IF(W55=0,0,IF(W55=X55,1,0)) -> 1
F56: Value | G56: Value | H56: Per Share | L56: Terminal Multiple | O56: ='Inputs-R'!$F$108 -> 7
F57: =Model!H540 -> 130862.76 | L57: WACC | O57: ='Inputs-R'!$L$84 -> 0.095866057 | S57: Learner | T57: Correct | U57: Compare | W57: Learner | X57: Correct | Y57: Compare
D58: =D14 -> Best Case | E58: 1 | F58: 130862.76 | G58: =F58-$O$58 -> 112220.76 | H58: =+G58/$O$59 -> 3.2813089 | L58: Net Debt | N58: =N14 -> (End of 2022) | O58: ='Inputs-R'!$L$94 -> 18642 | S58: =SUM(Outputs!E58:E60) -> 6 | T58: =SUM(E58:E60) -> 6 | U58: =IF(S58=0,0,IF(S58=T58,1,0)) -> 1 | W58: =IFERROR(_xlfn.FORMULATEXT(Outputs!F58),0) -> 0 | X58: =IFERROR(_xlfn.FORMULATEXT(F58),0) -> 0 | Y58: =IF(W58=0,0,IF(W58=X58,1,0)) -> 0
D59: =D15 -> Base Case | E59: 2 | F59: 130862.76 | G59: =F59-$O$58 -> 112220.76 | H59: =+G59/$O$59 -> 3.2813089 | L59: Shares Outstanding | N59: (FD 000) | O59: ='Inputs-R'!$F$105 -> 34200 | W59: =IFERROR(_xlfn.FORMULATEXT(Outputs!F59),0) -> 0 | X59: =IFERROR(_xlfn.FORMULATEXT(F59),0) -> 0 | Y59: =IF(W59=0,0,IF(W59=X59,1,0)) -> 0
D60: =D16 -> Worst Case | E60: 3 | F60: 130862.76 | G60: =F60-$O$58 -> 112220.76 | H60: =+G60/$O$59 -> 3.2813089 | L60: Current Stock Price | N60: (US$/sh) | O60: ='Inputs-R'!$F$106 -> 2.23 | W60: =IFERROR(_xlfn.FORMULATEXT(Outputs!F60),0) -> 0 | X60: =IFERROR(_xlfn.FORMULATEXT(F60),0) -> 0 | Y60: =IF(W60=0,0,IF(W60=X60,1,0)) -> 0
Y62: =IF(SUM(Y58:Y60)=3,1,0) -> 0
D64: Enterprise Value 1 | L64: Equity Value per Share | S64: Learner | T64: Correct | U64: Compare
S65: =Outputs!C67 -> 130862.76 | T65: =C67 -> 130862.76 | U65: =IF(S65=0,0,IF(S65=T65,1,0)) -> 1
D66: Terminal Multiple | L66: Terminal Multiple
C67: =Model!H540 -> 130862.76 | D67: =E67-0.5 -> 6 | E67: =F67-0.5 -> 6.5 | F67: ='Inputs-R'!F108 -> 7 | G67: =+F67+0.5 -> 7.5 | H67: =+G67+0.5 -> 8 | L67: =D67 -> 6 | M67: =E67 -> 6.5 | N67: =F67 -> 7 | O67: =G67 -> 7.5 | P67: =H67 -> 8 | S67: Learner | Y67: Correct | AE67: Compare
B68: WACC | C68: =C69-0.01 -> 0.075866057 | D68: 130862.76 | E68: 130862.76 | F68: 130862.76 | G68: 130862.76 | H68: 130862.76 | J68: WACC | K68: =C68 -> 0.075866057 | L68: =D81/$O$59 -> 3.2813089 | M68: =E81/$O$59 -> 3.2813089 | N68: =F81/$O$59 -> 3.2813089 | O68: =G81/$O$59 -> 3.2813089 | P68: =H81/$O$59 -> 3.2813089 | S68: =IFERROR(_xlfn.FORMULATEXT(Outputs!D68),0) -> 0 | T68: =IFERROR(_xlfn.FORMULATEXT(Outputs!E68),0) -> 0 | U68: =IFERROR(_xlfn.FORMULATEXT(Outputs!F68),0) -> 0 | V68: =IFERROR(_xlfn.FORMULATEXT(Outputs!G68),0) -> 0 | W68: =IFERROR(_xlfn.FORMULATEXT(Outputs!H68),0) -> 0 | Y68: =IFERROR(_xlfn.FORMULATEXT(D68),0) -> 0 | Z68: =IFERROR(_xlfn.FORMULATEXT(E68),0) -> 0 | AA68: =IFERROR(_xlfn.FORMULATEXT(F68),0) -> 0 | AB68: =IFERROR(_xlfn.FORMULATEXT(G68),0) -> 0 | AC68: =IFERROR(_xlfn.FORMULATEXT(H68),0) -> 0 | AE68: =IF(S68=Y68,1,0) -> 1 | AF68: =IF(T68=Z68,1,0) -> 1 | AG68: =IF(U68=AA68,1,0) -> 1 | AH68: =IF(V68=AB68,1,0) -> 1 | AI68: =IF(W68=AC68,1,0) -> 1
C69: =C70-0.01 -> 0.085866057 | D69: 130862.76 | E69: 130862.76 | F69: 130862.76 | G69: 130862.76 | H69: 130862.76 | K69: =C69 -> 0.085866057 | L69: =D82/$O$59 -> 3.2813089 | M69: =E82/$O$59 -> 3.2813089 | N69: =F82/$O$59 -> 3.2813089 | O69: =G82/$O$59 -> 3.2813089 | P69: =H82/$O$59 -> 3.2813089 | S69: =IFERROR(_xlfn.FORMULATEXT(Outputs!D69),0) -> 0 | T69: =IFERROR(_xlfn.FORMULATEXT(Outputs!E69),0) -> 0 | U69: =IFERROR(_xlfn.FORMULATEXT(Outputs!F69),0) -> 0 | V69: =IFERROR(_xlfn.FORMULATEXT(Outputs!G69),0) -> 0 | W69: =IFERROR(_xlfn.FORMULATEXT(Outputs!H69),0) -> 0 | Y69: =IFERROR(_xlfn.FORMULATEXT(D69),0) -> 0 | Z69: =IFERROR(_xlfn.FORMULATEXT(E69),0) -> 0 | AA69: =IFERROR(_xlfn.FORMULATEXT(F69),0) -> 0 | AB69: =IFERROR(_xlfn.FORMULATEXT(G69),0) -> 0 | AC69: =IFERROR(_xlfn.FORMULATEXT(H69),0) -> 0 | AE69: =IF(S69=Y69,1,0) -> 1 | AF69: =IF(T69=Z69,1,0) -> 1 | AG69: =IF(U69=AA69,1,0) -> 1 | AH69: =IF(V69=AB69,1,0) -> 1 | AI69: =IF(W69=AC69,1,0) -> 1
C70: ='Inputs-R'!$L$84 -> 0.095866057 | D70: 130862.76 | E70: 130862.76 | F70: 130862.76 | G70: 130862.76 | H70: 130862.76 | K70: =C70 -> 0.095866057 | L70: =D83/$O$59 -> 3.2813089 | M70: =E83/$O$59 -> 3.2813089 | N70: =F83/$O$59 -> 3.2813089 | O70: =G83/$O$59 -> 3.2813089 | P70: =H83/$O$59 -> 3.2813089 | S70: =IFERROR(_xlfn.FORMULATEXT(Outputs!D70),0) -> 0 | T70: =IFERROR(_xlfn.FORMULATEXT(Outputs!E70),0) -> 0 | U70: =IFERROR(_xlfn.FORMULATEXT(Outputs!F70),0) -> 0 | V70: =IFERROR(_xlfn.FORMULATEXT(Outputs!G70),0) -> 0 | W70: =IFERROR(_xlfn.FORMULATEXT(Outputs!H70),0) -> 0 | Y70: =IFERROR(_xlfn.FORMULATEXT(D70),0) -> 0 | Z70: =IFERROR(_xlfn.FORMULATEXT(E70),0) -> 0 | AA70: =IFERROR(_xlfn.FORMULATEXT(F70),0) -> 0 | AB70: =IFERROR(_xlfn.FORMULATEXT(G70),0) -> 0 | AC70: =IFERROR(_xlfn.FORMULATEXT(H70),0) -> 0 | AE70: =IF(S70=Y70,1,0) -> 1 | AF70: =IF(T70=Z70,1,0) -> 1 | AG70: =IF(U70=AA70,1,0) -> 1 | AH70: =IF(V70=AB70,1,0) -> 1 | AI70: =IF(W70=AC70,1,0) -> 1
C71: =C70+0.01 -> 0.10586606 | D71: 130862.76 | E71: 130862.76 | F71: 130862.76 | G71: 130862.76 | H71: 130862.76 | K71: =C71 -> 0.10586606 | L71: =D84/$O$59 -> 3.2813089 | M71: =E84/$O$59 -> 3.2813089 | N71: =F84/$O$59 -> 3.2813089 | O71: =G84/$O$59 -> 3.2813089 | P71: =H84/$O$59 -> 3.2813089 | S71: =IFERROR(_xlfn.FORMULATEXT(Outputs!D71),0) -> 0 | T71: =IFERROR(_xlfn.FORMULATEXT(Outputs!E71),0) -> 0 | U71: =IFERROR(_xlfn.FORMULATEXT(Outputs!F71),0) -> 0 | V71: =IFERROR(_xlfn.FORMULATEXT(Outputs!G71),0) -> 0 | W71: =IFERROR(_xlfn.FORMULATEXT(Outputs!H71),0) -> 0 | Y71: =IFERROR(_xlfn.FORMULATEXT(D71),0) -> 0 | Z71: =IFERROR(_xlfn.FORMULATEXT(E71),0) -> 0 | AA71: =IFERROR(_xlfn.FORMULATEXT(F71),0) -> 0 | AB71: =IFERROR(_xlfn.FORMULATEXT(G71),0) -> 0 | AC71: =IFERROR(_xlfn.FORMULATEXT(H71),0) -> 0 | AE71: =IF(S71=Y71,1,0) -> 1 | AF71: =IF(T71=Z71,1,0) -> 1 | AG71: =IF(U71=AA71,1,0) -> 1 | AH71: =IF(V71=AB71,1,0) -> 1 | AI71: =IF(W71=AC71,1,0) -> 1
C72: =C71+0.01 -> 0.11586606 | D72: 130862.76 | E72: 130862.76 | F72: 130862.76 | G72: 130862.76 | H72: 130862.76 | K72: =C72 -> 0.11586606 | L72: =D85/$O$59 -> 3.2813089 | M72: =E85/$O$59 -> 3.2813089 | N72: =F85/$O$59 -> 3.2813089 | O72: =G85/$O$59 -> 3.2813089 | P72: =H85/$O$59 -> 3.2813089 | S72: =IFERROR(_xlfn.FORMULATEXT(Outputs!D72),0) -> 0 | T72: =IFERROR(_xlfn.FORMULATEXT(Outputs!E72),0) -> 0 | U72: =IFERROR(_xlfn.FORMULATEXT(Outputs!F72),0) -> 0 | V72: =IFERROR(_xlfn.FORMULATEXT(Outputs!G72),0) -> 0 | W72: =IFERROR(_xlfn.FORMULATEXT(Outputs!H72),0) -> 0 | Y72: =IFERROR(_xlfn.FORMULATEXT(D72),0) -> 0 | Z72: =IFERROR(_xlfn.FORMULATEXT(E72),0) -> 0 | AA72: =IFERROR(_xlfn.FORMULATEXT(F72),0) -> 0 | AB72: =IFERROR(_xlfn.FORMULATEXT(G72),0) -> 0 | AC72: =IFERROR(_xlfn.FORMULATEXT(H72),0) -> 0 | AE72: =IF(S72=Y72,1,0) -> 1 | AF72: =IF(T72=Z72,1,0) -> 1 | AG72: =IF(U72=AA72,1,0) -> 1 | AH72: =IF(V72=AB72,1,0) -> 1 | AI72: =IF(W72=AC72,1,0) -> 1
AE74: =IF(SUM(AE68:AI72)=25,1,0) -> 1
D77: Equity Value | L77: Premium (Discount) to Stock Price
D79: Terminal Multiple | L79: Terminal Multiple
D80: =D67 -> 6 | E80: =E67 -> 6.5 | F80: =F67 -> 7 | G80: =G67 -> 7.5 | H80: =H67 -> 8 | L80: =D80 -> 6 | M80: =E80 -> 6.5 | N80: =F80 -> 7 | O80: =G80 -> 7.5 | P80: =H80 -> 8
B81: WACC | C81: =C68 -> 0.075866057 | D81: =D68-$O$58 -> 112220.76 | E81: =E68-$O$58 -> 112220.76 | F81: =F68-$O$58 -> 112220.76 | G81: =G68-$O$58 -> 112220.76 | H81: =H68-$O$58 -> 112220.76 | J81: WACC | K81: =C81 -> 0.075866057 | L81: =L68/$O$60-1 -> 0.47143897 | M81: =M68/$O$60-1 -> 0.47143897 | N81: =N68/$O$60-1 -> 0.47143897 | O81: =O68/$O$60-1 -> 0.47143897 | P81: =P68/$O$60-1 -> 0.47143897
C82: =C69 -> 0.085866057 | D82: =D69-$O$58 -> 112220.76 | E82: =E69-$O$58 -> 112220.76 | F82: =F69-$O$58 -> 112220.76 | G82: =G69-$O$58 -> 112220.76 | H82: =H69-$O$58 -> 112220.76 | K82: =C82 -> 0.085866057 | L82: =L69/$O$60-1 -> 0.47143897 | M82: =M69/$O$60-1 -> 0.47143897 | N82: =N69/$O$60-1 -> 0.47143897 | O82: =O69/$O$60-1 -> 0.47143897 | P82: =P69/$O$60-1 -> 0.47143897
C83: =C70 -> 0.095866057 | D83: =D70-$O$58 -> 112220.76 | E83: =E70-$O$58 -> 112220.76 | F83: =F70-$O$58 -> 112220.76 | G83: =G70-$O$58 -> 112220.76 | H83: =H70-$O$58 -> 112220.76 | K83: =C83 -> 0.095866057 | L83: =L70/$O$60-1 -> 0.47143897 | M83: =M70/$O$60-1 -> 0.47143897 | N83: =N70/$O$60-1 -> 0.47143897 | O83: =O70/$O$60-1 -> 0.47143897 | P83: =P70/$O$60-1 -> 0.47143897
C84: =C71 -> 0.10586606 | D84: =D71-$O$58 -> 112220.76 | E84: =E71-$O$58 -> 112220.76 | F84: =F71-$O$58 -> 112220.76 | G84: =G71-$O$58 -> 112220.76 | H84: =H71-$O$58 -> 112220.76 | K84: =C84 -> 0.10586606 | L84: =L71/$O$60-1 -> 0.47143897 | M84: =M71/$O$60-1 -> 0.47143897 | N84: =N71/$O$60-1 -> 0.47143897 | O84: =O71/$O$60-1 -> 0.47143897 | P84: =P71/$O$60-1 -> 0.47143897
C85: =C72 -> 0.11586606 | D85: =D72-$O$58 -> 112220.76 | E85: =E72-$O$58 -> 112220.76 | F85: =F72-$O$58 -> 112220.76 | G85: =G72-$O$58 -> 112220.76 | H85: =H72-$O$58 -> 112220.76 | K85: =C85 -> 0.11586606 | L85: =L72/$O$60-1 -> 0.47143897 | M85: =M72/$O$60-1 -> 0.47143897 | N85: =N72/$O$60-1 -> 0.47143897 | O85: =O72/$O$60-1 -> 0.47143897 | P85: =P72/$O$60-1 -> 0.47143897
P87: These tables require the workbook calculation to be set to automatic to update. | S87: =IF(SUM(U58+Y55+Y62+U65+AE74)=5,"COMPLETE","")

Sheet Inputs
B3: Drivers
B5: All figures in USD thousands unless stated | G5: =$F$105 -> 2023 | H5: =G5+1 -> 2024 | I5: =H5+1 -> 2025 | J5: =I5+1 -> 2026 | K5: =J5+1 -> 2027 | L5: Term
B7: Driver Switch | D7: =Outputs!F6 -> 2
B10: Revenue Growth | G10: =CHOOSE($D$7,G12,G13,G14) -> 0.03 | H10: =CHOOSE($D$7,H12,H13,H14) -> 0.02 | I10: =CHOOSE($D$7,I12,I13,I14) -> 0.02 | J10: =CHOOSE($D$7,J12,J13,J14) -> 0.015 | K10: =CHOOSE($D$7,K12,K13,K14) -> 0.015 | L10: =CHOOSE($D$7,L12,L13,L14) -> 0.01
B12: =Outputs!D14 -> Best Case | G12: 0.04 | H12: 0.03 | I12: 0.025 | J12: 0.02 | K12: 0.02 | L12: 0.015
B13: =Outputs!D15 -> Base Case | G13: 0.03 | H13: 0.02 | I13: 0.02 | J13: 0.015 | K13: 0.015 | L13: 0.01
B14: =Outputs!D16 -> Worst Case | G14: 0.01 | H14: 0.01 | I14: 0.005 | J14: 0.005 | K14: 0.005 | L14: 0.005
B17: Cost projection Increases | G17: =CHOOSE($D$7,G19,G20,G21) -> 0.035 | H17: =CHOOSE($D$7,H19,H20,H21) -> 0.03 | I17: =CHOOSE($D$7,I19,I20,I21) -> 0.03 | J17: =CHOOSE($D$7,J19,J20,J21) -> 0.025 | K17: =CHOOSE($D$7,K19,K20,K21) -> 0.025 | L17: =CHOOSE($D$7,L19,L20,L21) -> 0.015
B19: =$B$12 -> Best Case | G19: 0.035 | H19: 0.02 | I19: 0.02 | J19: 0.02 | K19: 0.015 | L19: 0.008
B20: =$B$13 -> Base Case | G20: 0.035 | H20: 0.03 | I20: 0.03 | J20: 0.025 | K20: 0.025 | L20: 0.015
B21: =$B$14 -> Worst Case | G21: 0.05 | H21: 0.04 | I21: 0.04 | J21: 0.035 | K21: 0.03 | L21: 0.03
B24: Capital Expenditure | G24: =CHOOSE($D$7,G26,G27,G28) -> 10000 | H24: =CHOOSE($D$7,H26,H27,H28) -> 8000 | I24: =CHOOSE($D$7,I26,I27,I28) -> 9000 | J24: =CHOOSE($D$7,J26,J27,J28) -> 5000 | K24: =CHOOSE($D$7,K26,K27,K28) -> 5000 | L24: =CHOOSE($D$7,L26,L27,L28) -> 6000
B26: =$B$12 -> Best Case | G26: 4000 | H26: 4300 | I26: 4400 | J26: 4600 | K26: 4800 | L26: 4900
B27: =$B$13 -> Base Case | G27: 10000 | H27: 8000 | I27: 9000 | J27: 5000 | K27: 5000 | L27: 6000
B28: =$B$14 -> Worst Case | G28: 5000 | H28: 5200 | I28: 5400 | J28: 5500 | K28: 5600 | L28: 5800
B31: Inflation Rate | G31: 0.035 | H31: 0.03 | I31: 0.03 | J31: 0.025 | K31: 0.025 | L31: 0.015
B34: Working Capital 1
B35: Accounts Receivable | E35: (Days) | G35: 45 | H35: 45 | I35: 45 | J35: 45 | K35: 45 | L35: =K35 -> 45
B36: Inventory | E36: (Days) | G36: 25 | H36: 25 | I36: 25 | J36: 25 | K36: 25 | L36: =K36 -> 25
B37: Accounts Payable | E37: (Days) | G37: 40 | H37: 40 | I37: 40 | J37: 40 | K37: 40 | L37: =K37 -> 40
B40: Other Annual Inputs
A41: - | B41: Term Debt | E41: Increase / (Decrease) | G41: -3000 | H41: -3000 | I41: -2000 | J41: -3000 | K41: -3000 | L41: -2000
B42: Common Equity | E42: Increase / (Decrease) | G42: -1000 | H42: -1000 | I42: -1000 | J42: -1000 | K42: -1000 | L42: -1000
B43: ='Inputs-R'!Q39 | L43: We have assumed working capital amounts per day in terminal year are equal to the previous year.
B47: Weighted Average Cost of Capital
B49: All figures in USD thousands unless stated
H51: Average | I51: Debt/ | J51: Debt/ | K51: Levered | L51: Unlevered
B52: Name | C52: Industry | D52: Region | E52: Market | F52: Debt | G52: Equity | H52: Tax Rate 1 | I52: Equity | J52: Capital | K52: Beta 2 | L52: Beta 3
B54: Peer 1 | C54: Industry 1 | D54: Canada | F54: 88888 | G54: 9999999 | H54: 0.315 | I54: =F54/G54 -> 0.0088888009 | J54: =F54/(F54+G54) -> 0.0088104862 | K54: 0.85 | L54: =K54/(1+(1-H54)*(I54)) -> 0.84485582
B55: Peer 2 | C55: Industry 2 | D55: USA | F55: 88888 | G55: 9999999 | H55: 0.315 | I55: =F55/G55 -> 0.0088888009 | J55: =F55/(F55+G55) -> 0.0088104862 | K55: 0.85 | L55: =K55/(1+(1-H55)*(I55)) -> 0.84485582
B56: Peer 3 | C56: Industry 3 | D56: USA | F56: 88888 | G56: 9999999 | H56: 0.315 | I56: =F56/G56 -> 0.0088888009 | J56: =F56/(F56+G56) -> 0.0088104862 | K56: 0.85 | L56: =K56/(1+(1-H56)*(I56)) -> 0.84485582
B57: Peer 4 | C57: Industry 4 | D57: USA | F57: 88888 | G57: 9999999 | H57: 0.315 | I57: =F57/G57 -> 0.0088888009 | J57: =F57/(F57+G57) -> 0.0088104862 | K57: 0.85 | L57: =K57/(1+(1-H57)*(I57)) -> 0.84485582
B58: Peer 5 | C58: Industry 5 | D58: Canada | F58: 88888 | G58: 9999999 | H58: 0.315 | I58: =F58/G58 -> 0.0088888009 | J58: =F58/(F58+G58) -> 0.0088104862 | K58: 0.85 | L58: =K58/(1+(1-H58)*(I58)) -> 0.84485582
B59: Peer 6 | C59: Industry 6 | D59: Canada | F59: 88888 | G59: 9999999 | H59: 0.315 | I59: =F59/G59 -> 0.0088888009 | J59: =F59/(F59+G59) -> 0.0088104862 | K59: 0.85 | L59: =K59/(1+(1-H59)*(I59)) -> 0.84485582
B60: Peer 7 | C60: Industry 7 | D60: USA | F60: 88888 | G60: 9999999 | H60: 0.315 | I60: =F60/G60 -> 0.0088888009 | J60: =F60/(F60+G60) -> 0.0088104862 | K60: 0.85 | L60: =K60/(1+(1-H60)*(I60)) -> 0.84485582
B61: Peer 8 | C61: Industry 8 | D61: Canada | F61: 88888 | G61: 9999999 | H61: 0.315 | I61: =F61/G61 -> 0.0088888009 | J61: =F61/(F61+G61) -> 0.0088104862 | K61: 0.85 | L61: =K61/(1+(1-H61)*(I61)) -> 0.84485582
B62: Peer 9 | C62: Industry 9 | D62: Ghana | F62: 88888 | G62: 9999999 | H62: 0.315 | I62: =F62/G62 -> 0.0088888009 | J62: =F62/(F62+G62) -> 0.0088104862 | K62: 0.99399 | L62: =K62/(1+(1-H62)*(I62)) -> 0.98797439
B63: Peer 10 | C63: Industry 10 | D63: China | F63: 88888 | G63: 9999999 | H63: 0.315 | I63: =F63/G63 -> 0.0088888009 | J63: =F63/(F63+G63) -> 0.0088104862 | K63: 0.88324 | L63: =K63/(1+(1-H63)*(I63)) -> 0.87789465
I64: ='Inputs-R'!Q51 -> 0 | J64: ='Inputs-R'!U51 -> 0 | L64: ='Inputs-R'!Y51 -> 0
G65: Average | H65: =AVERAGE(H54:H63) -> 0.315 | I65: =AVERAGE(I54:I63) -> 0.0088888009 | J65: =AVERAGE(J54:J63) -> 0.0088104862 | K65: =AVERAGE(K54:K63) -> 0.867723 | L65: =AVERAGE(L54:L63) -> 0.86247156
G66: Median | H66: =MEDIAN(H54:H63) -> 0.315 | I66: =MEDIAN(I54:I63) -> 0.0088888009 | J66: =MEDIAN(J54:J63) -> 0.0088104862 | K66: =MEDIAN(K54:K63) -> 0.85 | L66: =MEDIAN(L54:L63) -> 0.84485582
B69: Risk Premium for Equity | H69: Cost of Equity
B71: Market Risk Premium | F71: 0.047 | H71: Risk Free Rate | L71: 0.024
B72: Average Unlevered Beta | F72: =L65 -> 0.86247156 | H72: Equity Risk Premium | L72: =F74 -> 0.045901244
B73: Levered Beta 4 | F73: =F72*(1+(1-L81)*F85) -> 0.97662221 | H73: Country Risk Premium | L73: 0.036
B74: Equity Risk Premium | F74: =F71*F73 -> 0.045901244 | H74: Cost of Equity | L74: =SUM(L71:L73) -> 0.10590124
B78: Capital Structure | H78: Cost of Debt
E80: Current | F80: Target | H80: Pre-Tax Cost of Debt | L80: 0.052
B81: Total Debt | D81: 19102 | E81: =D81/D83 -> 0.13153654 | F81: 0.15 | H81: Tax Rate | L81: 0.25
B82: Market Capitalization | D82: 126120 | E82: =D82/D83 -> 0.86846346 | F82: 0.85 | H82: After-Tax Cost of Debt | L82: =L80*(1-L81) -> 0.039
B83: Total Capitalization | D83: =SUM(D81:D82) -> 145222 | E83: =SUM(E81:E82) -> 1 | F83: =SUM(F81:F82) -> 1
B85: Debt / Equity | E85: =E81/E82 -> 0.15145893 | F85: =F81/F82 -> 0.17647059 | H85: Weighted Average Cost of Capital
K87: Weight | L87: Cost
B88: Tax Rate is a 5-Year Average. | H88: Debt Capital | K88: =F81 -> 0.15 | L88: =L82 -> 0.039
B89: Levered beta is based on 5-year monthly data. | H89: Equity Capital | K89: =F82 -> 0.85 | L89: =L74 -> 0.10590124
B90: Unlevered Beta = Levered Beta / (1 + (1 - Tax Rate) × Debt-to-Equity)
B91: Levered Beta = Unlevered Beta x (1 + (1 - Tax rate) x (Debt-to-Equity))
H92: Weighted Average Cost of Capital | L92: =K88*L88+K89*L89 -> 0.095866057
B93: ='Inputs-R'!Y86
B96: Other Inputs
B98: All figures in USD thousands unless stated
B101: Dates | H101: =CONCATENATE("End of ",G5-1," Balances") -> End of 2022 Balances
B102: Valuation Date | E102: (YY-MM-DD) | F102: 45016 | H102: Net Debt | L102: 18642
B103: First Expected Cash Flow | E103: (YY-MM-DD) | F103: 45107 | H103: Property Plant & Equipment | L103: 75407
B104: First Fiscal Year End for Forecast | E104: (YY-MM-DD) | F104: 45291 | H104: Tax Basis for PP&E | L104: 39211
B105: First Year of Forecast | E105: (YYYY) | F105: =YEAR(F104) -> 2023 | H105: Tax Losses | L105: 24128
B106: Incorrect Date Set for Valuation? | F106: =IF(F102>F103,1,0) -> 0 | H106: 52 Week High | L106: 5
B107: Incorrect Date Set for First Cash Flow? | F107: =IF(F103>F104,1,0) -> 0 | H107: 52 Week Low | L107: 3.2
B108: Days in Period | F108: 365
H111: Other Inputs
B112: Valuation | H112: First Year Tax Depreciation | L112: 0.5
B113: Shares Outstanding | E113: (FD 000) | F113: 34200 | H113: Blended Tax Depreciation Rate | L113: 0.15
B114: Current Stock Price | E114: (US$/sh) | F114: 2.23 | H114: First Year Accounting Depreciation | L114: 0.5
B115: Terminal Growth Rate | F115: =L10 -> 0.01 | H115: Useful Life: Existing Assets | K115: (Years) | L115: 16
B116: Terminal EBITDA Multiple 1 | F116: 7 | H116: Useful Life: New Assets | K116: (Years) | L116: 20
B117: Weighted Average Cost of Capital (WACC) | F117: =L92 -> 0.095866057 | H117: Dividend Payout Ratio | L117: 0.2
B118: Terminal Growth Greater Than or Equal To WACC? | F118: =IF(F115>=F117,1,0) -> 0
B120: Interest Rates
B121: Cash Balances | F121: 0.01
B122: Revolving Credit Line | F122: 0.05
B123: Long Term Debt | F123: 0.06 | L123: The Terminal EBITDA multiple should reflect a 'steady-state' industry multiple.
B125: ='Inputs-R'!Q112 -> COMPLETE

Sheet Inputs-R
B3: Drivers
B5: All figures in USD thousands unless stated | G5: =$F$97 -> 2023 | H5: =G5+1 -> 2024 | I5: =H5+1 -> 2025 | J5: =I5+1 -> 2026 | K5: =J5+1 -> 2027 | L5: Term
B7: Driver Switch | D7: ='Outputs-R'!F6 -> 2
O9: Learner | P9: Correct | Q9: Compare
B10: Sales Volume Growth | G10: {=INDEX(G12:G14,$D$7)} -> 0.02 | H10: {=INDEX(H12:H14,$D$7)} -> 0.01 | I10: {=INDEX(I12:I14,$D$7)} -> 0.01 | J10: {=INDEX(J12:J14,$D$7)} -> 0.005 | K10: {=INDEX(K12:K14,$D$7)} -> 0.005 | L10: {=INDEX(L12:L14,$D$7)} -> 0.005 | O10: =SUM(Inputs!G10:L10) -> 0.11 | P10: =SUM(G10:L10) -> 0.055 | Q10: =IF(O10=0,0,IF(O10=P10,1,0)) -> 0
B12: =Outputs!D14 -> Best Case | G12: 0.03 | H12: 0.02 | I12: 0.02 | J12: 0.015 | K12: 0.015 | L12: 0.01
B13: =Outputs!D15 -> Base Case | G13: 0.02 | H13: 0.01 | I13: 0.01 | J13: 0.005 | K13: 0.005 | L13: 0.005
B14: =Outputs!D16 -> Worst Case | G14: 0.01 | H14: 0.01 | I14: 0.005 | J14: 0.005 | K14: 0.005 | L14: 0.005
O16: Learner | P16: Correct | Q16: Compare
B17: Pricing Increases | G17: {=INDEX(G19:G21,$D$7)} -> 0.03 | H17: {=INDEX(H19:H21,$D$7)} -> 0.01 | I17: {=INDEX(I19:I21,$D$7)} -> 0.01 | J17: {=INDEX(J19:J21,$D$7)} -> 0.01 | K17: {=INDEX(K19:K21,$D$7)} -> 0.005 | L17: {=INDEX(L19:L21,$D$7)} -> 0.005 | O17: =SUM(Inputs!G17:L17) -> 0.16 | P17: =SUM(G17:L17) -> 0.07 | Q17: =IF(O17=0,0,IF(O17=P17,1,0)) -> 0
B19: =$B$12 -> Best Case | G19: 0.035 | H19: 0.02 | I19: 0.02 | J19: 0.02 | K19: 0.015 | L19: 0.008
B20: =$B$13 -> Base Case | G20: 0.03 | H20: 0.01 | I20: 0.01 | J20: 0.01 | K20: 0.005 | L20: 0.005
B21: =$B$14 -> Worst Case | G21: 0.01 | H21: 0.01 | I21: 0.005 | J21: 0.005 | K21: 0.005 | L21: 0.005
O23: Learner | P23: Correct | Q23: Compare
B24: Capital Expenditure | G24: {=INDEX(G26:G28,$D$7)} -> 4550 | H24: {=INDEX(H26:H28,$D$7)} -> 4700 | I24: {=INDEX(I26:I28,$D$7)} -> 4850 | J24: {=INDEX(J26:J28,$D$7)} -> 5000 | K24: {=INDEX(K26:K28,$D$7)} -> 5125 | L24: {=INDEX(L26:L28,$D$7)} -> 5300 | O24: =SUM(Inputs!G24:L24) -> 43000 | P24: =SUM(G24:L24) -> 29525 | Q24: =IF(O24=0,0,IF(O24=P24,1,0)) -> 0
B26: =$B$12 -> Best Case | G26: 4000 | H26: 4300 | I26: 4400 | J26: 4600 | K26: 4800 | L26: 4900
B27: =$B$13 -> Base Case | G27: 4550 | H27: 4700 | I27: 4850 | J27: 5000 | K27: 5125 | L27: 5300
B28: =$B$14 -> Worst Case | G28: 5000 | H28: 5200 | I28: 5400 | J28: 5500 | K28: 5600 | L28: 5800
B31: Inflation Rate | G31: 0.035 | H31: 0.03 | I31: 0.03 | J31: 0.025 | K31: 0.025 | L31: 0.015
B34: Working Capital 1 | O34: Learner | P34: Correct | Q34: Compare
B35: Accounts Receivable | E35: (Days) | G35: 45 | H35: 45 | I35: 45 | J35: 45 | K35: 45 | L35: =K35 -> 45 | O35: =Inputs!L35 -> 45 | P35: =L35 -> 45 | Q35: =IF(O35=0,0,IF(O35=P35,1,0)) -> 1
B36: Inventory | E36: (Days) | G36: 25 | H36: 25 | I36: 25 | J36: 25 | K36: 25 | L36: =K36 -> 25 | O36: =Inputs!L36 -> 25 | P36: =L36 -> 25 | Q36: =IF(O36=0,0,IF(O36=P36,1,0)) -> 1
B37: Accounts Payable | E37: (Days) | G37: 40 | H37: 40 | I37: 40 | J37: 40 | K37: 40 | L37: =K37 -> 40 | O37: =Inputs!L37 -> 40 | P37: =L37 -> 40 | Q37: =IF(O37=0,0,IF(O37=P37,1,0)) -> 1
Q39: =IF(SUM(Q9:Q37)=6,"COMPLETE","")
L40: We have assumed working capital amounts per day in terminal year are equal to the previous year.
B44: Weighted Average Cost of Capital
B46: All figures in USD thousands unless stated
H48: Average | I48: Debt/ | J48: Debt/ | K48: Levered | L48: Unlevered
B49: Name | D49: Region | F49: Debt | G49: Equity | H49: Tax Rate 1 | I49: Equity | J49: Capital | K49: Beta 2 | L49: Beta 3
O50: Learner | P50: Correct | Q50: Compare | S50: Learner | T50: Correct | U50: Compare | W50: Learner | X50: Correct | Y50: Compare
B51: Surge Batteries Inc. | D51: Europe | F51: 63702 | G51: 375499.31 | H51: 0.315 | I51: =F51/G51 -> 0.16964612 | J51: =F51/(F51+G51) -> 0.14504055 | K51: 0.85 | L51: =K51/(1+(1-H51)*Inputs!I54) -> 0.84485582 | O51: =SUM(Inputs!I54:I63) -> 0.088888009 | P51: =SUM(I51:I55) -> 0.80833165 | Q51: =IF(O51=0,0,IF(O51=P51,1,0)) -> 0 | S51: =SUM(Inputs!J54:J63) -> 0.088104862 | T51: =SUM(J51:J55) -> 0.6943955 | U51: =IF(S51=0,0,IF(S51=T51,1,0)) -> 0 | W51: =SUM(Inputs!L54:L63) -> 8.6247156 | X51: =SUM(L51:L55) -> 5.0433718 | Y51: =IF(W51=0,0,IF(W51=X51,1,0)) -> 0
B52: Future Energy Co. | D52: Europe | F52: 43422 | G52: 311425.2 | H52: 0.322 | I52: =F52/G52 -> 0.13942995 | J52: =F52/(F52+G52) -> 0.12236816 | K52: 1.01098 | L52: =K52/(1+(1-H52)*Inputs!I60) -> 1.0049237
B53: Clean Green Ltd. | D53: Europe | F53: 26211 | G53: 131995.56 | H53: 0.319 | I53: =F53/G53 -> 0.19857487 | J53: =F53/(F53+G53) -> 0.16567581 | K53: 1.33573 | L53: =K53/(1+(1-H53)*Inputs!I61) -> 1.3276931
B54: Full Power Solutions Ltd. | D54: Europe | F54: 15109 | G54: 95746.138 | H54: 0.33 | I54: =F54/G54 -> 0.15780271 | J54: =F54/(F54+G54) -> 0.13629499 | K54: 0.99399 | L54: =K54/(1+(1-H54)*Inputs!I62) -> 0.98810534
B55: Earthcor Power Inc. | D55: Europe | F55: 95234 | G55: 666540.63 | H55: 0.302 | I55: =F55/G55 -> 0.14287801 | J55: =F55/(F55+G55) -> 0.12501598 | K55: 0.88324 | L55: =K55/(1+(1-H55)*Inputs!I63) -> 0.87779383
G57: Average | H57: =AVERAGE(H51:H55) -> 0.3176 | I57: =AVERAGE(I51:I55) -> 0.16166633 | J57: =AVERAGE(J51:J55) -> 0.1388791 | K57: =AVERAGE(K51:K55) -> 1.014788 | L57: =AVERAGE(L51:L55) -> 1.0086744
G58: Median | H58: =MEDIAN(H51:H55) -> 0.319 | I58: =MEDIAN(I51:I55) -> 0.15780271 | J58: =MEDIAN(J51:J55) -> 0.13629499 | K58: =MEDIAN(K51:K55) -> 0.99399 | L58: =MEDIAN(L51:L55) -> 0.98810534
B61: Risk Premium for Equity | H61: Cost of Equity
B63: Market Risk Premium | F63: 0.047 | H63: Risk Free Rate | L63: 0.024 | O63: Learner | P63: Correct | Q63: Compare | S63: Learner | T63: Correct | U63: Compare
B64: Average Unlevered Beta | F64: =Inputs!L65 -> 0.86247156 | H64: Equity Risk Premium | L64: =Inputs!F74 -> 0.045901244 | O64: =Inputs!F72 -> 0.86247156 | P64: =F64 -> 0.86247156 | Q64: =IF(O64=0,0,IF(O64=P64,1,0)) -> 1 | S64: =Inputs!L72 -> 0.045901244 | T64: =L64 -> 0.045901244 | U64: =IF(S64=0,0,IF(S64=T64,1,0)) -> 1
B65: Levered Beta 4 | F65: =F64*(1+(1-L73)*Inputs!F85) -> 0.96901216 | H65: Country Risk Premium | L65: 0.036 | O65: =Inputs!F73 -> 0.97662221 | P65: =F65 -> 0.96901216 | Q65: =IF(O65=0,0,IF(O65=P65,1,0)) -> 0
B66: Equity Risk Premium | F66: =F63*Inputs!F73 -> 0.045901244 | H66: Cost of Equity | L66: =SUM(Inputs!L71:L73) -> 0.10590124 | O66: =Inputs!F74 -> 0.045901244 | P66: =F66 -> 0.045901244 | Q66: =IF(O66=0,0,IF(O66=P66,1,0)) -> 1 | S66: =Inputs!L74 -> 0.10590124 | T66: =L66 -> 0.10590124 | U66: =IF(S66=0,0,IF(S66=T66,1,0)) -> 1
B70: Capital Structure | H70: Cost of Debt
E72: Current | F72: Target | H72: Pre-Tax Cost of Debt | L72: 0.052 | O72: Learner | P72: Correct | Q72: Compare | W72: Learner | X72: Correct | Y72: Compare
B73: Total Debt | D73: 19102 | E73: =D73/$D$75 -> 0.13153654 | F73: 0.15 | H73: Tax Rate | L73: 0.3 | O73: =SUM(Inputs!E81:F81) -> 0.28153654 | P73: =SUM(E73:F73) -> 0.28153654 | Q73: =IF(O73=0,0,IF(O73=P73,1,0)) -> 1
B74: Market Capitalization | D74: 126120 | E74: =D74/$D$75 -> 0.86846346 | F74: =1-F73 -> 0.85 | H74: After-Tax Cost of Debt | L74: =L72*(1-L73) -> 0.0364 | O74: =SUM(Inputs!E82:F82) -> 1.7184635 | P74: =SUM(E74:F74) -> 1.7184635 | Q74: =IF(O74=0,0,IF(O74=P74,1,0)) -> 1 | W74: =Inputs!L82 -> 0.039 | X74: =L74 -> 0.0364 | Y74: =IF(W74=0,0,IF(W74=X74,1,0)) -> 0
B75: Total Capitalization | D75: =SUM(D73:D74) -> 145222 | E75: =SUM(E73:E74) -> 1 | F75: =SUM(F73:F74) -> 1 | O75: =SUM(Inputs!E83:F83) -> 2 | P75: =SUM(E75:F75) -> 2 | Q75: =IF(O75=0,0,IF(O75=P75,1,0)) -> 1
B77: Debt / Equity | E77: =Inputs!E81/Inputs!E82 -> 0.15145893 | F77: =Inputs!F81/Inputs!F82 -> 0.17647059 | H77: Weighted Average Cost of Capital | O77: =SUM(Inputs!E85:F85) -> 0.32792952 | P77: =SUM(E77:F77) -> 0.32792952 | Q77: =IF(O77=0,0,IF(O77=P77,1,0)) -> 1
K79: Weight | L79: Cost | S79: Learner | T79: Correct | U79: Compare | W79: Learner | X79: Correct | Y79: Compare
B80: Tax Rate is a 5-Year Average. | H80: Debt Capital | K80: =F73 -> 0.15 | L80: =Inputs!L82 -> 0.039 | S80: =Inputs!K88 -> 0.15 | T80: =K80 -> 0.15 | U80: =IF(S80=0,0,IF(S80=T80,1,0)) -> 1 | W80: =Inputs!L88 -> 0.039 | X80: =L80 -> 0.039 | Y80: =IF(W80=0,0,IF(W80=X80,1,0)) -> 1
B81: Levered beta is based on 5-year monthly data. | H81: Equity Capital | K81: =Inputs!F82 -> 0.85 | L81: =Inputs!L74 -> 0.10590124 | S81: =Inputs!K89 -> 0.85 | T81: =K81 -> 0.85 | U81: =IF(S81=0,0,IF(S81=T81,1,0)) -> 1 | W81: =Inputs!L89 -> 0.10590124 | X81: =L81 -> 0.10590124 | Y81: =IF(W81=0,0,IF(W81=X81,1,0)) -> 1
B82: Unlevered Beta = Levered Beta / (1 + (1 - Tax Rate) × Debt-to-Equity)
B83: Levered Beta = Unlevered Beta x (1 + (1 - Tax rate) x (Debt-to-Equity))
H84: Weighted Average Cost of Capital | L84: =SUMPRODUCT(Inputs!K88:K89,Inputs!L88:L89) -> 0.095866057 | W84: =Inputs!L92 -> 0.095866057 | X84: =L84 -> 0.095866057 | Y84: =IF(W84=0,0,IF(W84=X84,1,0)) -> 1
Y86: =IF(SUM(Y50:Y84)+SUM(U50:U84)+SUM(Q50:Q84)=18,"COMPLETE","")
B88: Other Inputs
B90: All figures in USD thousands unless stated
B93: Dates | H93: =CONCATENATE("End of ",G5-1," Balances") -> End of 2022 Balances
B94: Valuation Date | E94: (YY-MM-DD) | F94: 45016 | H94: Net Debt | L94: 18642
B95: First Expected Cash Flow | E95: (YY-MM-DD) | F95: 45107 | H95: Property Plant & Equipment | L95: 65014
B96: First Fiscal Year End for Forecast | E96: (YY-MM-DD) | F96: 45291 | H96: Tax Basis for PP&E | L96: 39211
B97: First Year of Forecast | E97: (YYYY) | F97: =YEAR(F96) -> 2023 | H97: Tax Losses | L97: 24128
B98: Incorrect Date Set for Valuation? | F98: =IF(F94>F95,1,0) -> 0
B99: Incorrect Date Set for First Cash Flow? | F99: =IF(F95>F96,1,0) -> 0
B100: Days in Period | F100: 365
H103: Other Inputs
B104: Valuation | H104: Plant Capacity | K104: (Units/Day) | L104: 1600
B105: Shares Outstanding | E105: (FD 000) | F105: 34200 | H105: Projected Interest Expense | L105: 2520
B106: Current Stock Price | E106: (US$/sh) | F106: 2.23 | H106: First Year Tax Depreciation | L106: 0.5
B107: Terminal Growth Rate | F107: 0.02 | H107: Blended Tax Depreciation Rate | L107: 0.15
B108: Terminal EBITDA Multiple 1 | F108: 7 | H108: First Year Accounting Depreciation | L108: 0.5 | O108: Learner | P108: Correct | Q108: Compare
B109: Weighted Average Cost of Capital (WACC) | F109: =Inputs!L92 -> 0.095866057 | H109: Useful Life: Existing Assets | K109: (Years) | L109: 16 | O109: =Inputs!F117 -> 0.095866057 | P109: =F109 -> 0.095866057 | Q109: =IF(O109=0,0,IF(O109=P109,1,0)) -> 1
B110: Terminal Growth Greater Than or Equal To WACC? | F110: =IF(F107>=Inputs!F117,1,0) -> 0 | H110: Useful Life: New Assets | K110: (Years) | L110: 20 | O110: =Inputs!F118 -> 0 | P110: =F110 -> 0 | Q110: =IF(ISBLANK(Inputs!F118),0,IF(O110=P110,1,0)) -> 1
Q112: =IF(SUM(Q109:Q110)=2,"COMPLETE","") -> COMPLETE
L113: The Terminal EBITDA multiple should reflect a 'steady-state' industry multiple.

Sheet Model
B3: All figures in USD thousands unless stated | F3: =G3-1 -> 2020 | G3: =H3-1 -> 2021 | H3: =I3-1 -> 2022 | I3: =Inputs!$F$105 -> 2023 | J3: =I3+1 -> 2024 | K3: =J3+1 -> 2025 | L3: =K3+1 -> 2026 | M3: =L3+1 -> 2027 | N3: Term
B4: {=CONCATENATE("Model Running: ",INDEX(Inputs!$B$12:$B$14,Inputs!$D$7)," Drivers")} -> Model Running: Base Case Drivers
B6: Days in Period | C6: =Inputs!$F$108 -> 365 | F6: 365 | G6: 365 | H6: 365 | I6: =$C$6 -> 365 | J6: =$C$6 -> 365 | K6: =$C$6 -> 365 | L6: =$C$6 -> 365 | M6: =$C$6 -> 365 | N6: =$C$6 -> 365
B7: Projected Cost Increase | F7: 0.024 | G7: 0.022 | H7: 0.023 | I7: =Inputs!G17 -> 0.035 | J7: =Inputs!H17 -> 0.03 | K7: =Inputs!I17 -> 0.03 | L7: =Inputs!J17 -> 0.025 | M7: =Inputs!K17 -> 0.025 | N7: =Inputs!L17 -> 0.015
B9: Income Statement
B11: All figures in USD thousands unless stated | F11: =F$3 -> 2020 | G11: =G$3 -> 2021 | H11: =H$3 -> 2022 | I11: =I$3 -> 2023 | J11: =J$3 -> 2024 | K11: =K$3 -> 2025 | L11: =L$3 -> 2026 | M11: =M$3 -> 2027 | N11: =N$3 -> Term
B12: =$B$4 -> Model Running: Base Case Drivers
B14: Inflation Rate | F14: 0.024 | G14: 0.022 | H14: 0.023 | I14: =Inputs!G31 -> 0.035 | J14: =Inputs!H31 -> 0.03 | K14: =Inputs!I31 -> 0.03 | L14: =Inputs!J31 -> 0.025 | M14: =Inputs!K31 -> 0.025 | N14: =Inputs!L31 -> 0.015
B17: Tax Rate | C17: =Inputs!$L$81 -> 0.25
B19: Revenue | F19: 50589 | G19: 51647.865 | H19: 53760.85 | I19: =H19*(1+Inputs!G10) -> 55373.675 | J19: =I19*(1+Inputs!H10) -> 56481.149 | K19: =J19*(1+Inputs!I10) -> 57610.772 | L19: =K19*(1+Inputs!J10) -> 58474.934 | M19: =L19*(1+Inputs!K10) -> 59352.058 | N19: =M19*(1+Inputs!L10) -> 59945.578 | P19: ok
B20: COGS | F20: -24544.3 | G20: -25104.014 | H20: -25779.401 | I20: =H20*(1+I7) -> -26681.681 | J20: =I20*(1+J7) -> -27482.131 | K20: =J20*(1+K7) -> -28306.595 | L20: =K20*(1+L7) -> -29014.26 | M20: =L20*(1+M7) -> -29739.616 | N20: =M20*(1+N7) -> -30185.711 | P20: ok
B21: Gross Profit | F21: =F19+F20 -> 26044.7 | G21: =G19+G20 -> 26543.851 | H21: =H19+H20 -> 27981.448 | I21: =I19+I20 -> 28691.995 | J21: =J19+J20 -> 28999.018 | K21: =K19+K20 -> 29304.177 | L21: =L19+L20 -> 29460.674 | M21: =M19+M20 -> 29612.441 | N21: =N19+N20 -> 29759.868 | P21: ok
B24: SG&A | F24: -5877 | G24: -6006 | H24: -6144 | I24: =H24*(1+I14) -> -6359.04 | J24: =I24*(1+J14) -> -6549.8112 | K24: =J24*(1+K14) -> -6746.3055 | L24: =K24*(1+L14) -> -6914.9632 | M24: =L24*(1+M14) -> -7087.8373 | N24: =M24*(1+N14) -> -7194.1548 | P24: ok
B25: Other | F25: -1764 | G25: -1931 | H25: -2026 | I25: =H25*(1+I14) -> -2096.91 | J25: =I25*(1+J14) -> -2159.8173 | K25: =J25*(1+K14) -> -2224.6118 | L25: =K25*(1+L14) -> -2280.2271 | M25: =L25*(1+M14) -> -2337.2328 | N25: =M25*(1+N14) -> -2372.2913 | P25: ok
B26: EBITDA | F26: =F21+SUM(F24:F25) -> 18403.7 | G26: =G21+SUM(G24:G25) -> 18606.851 | H26: =H21+SUM(H24:H25) -> 19811.448 | I26: =I21+SUM(I24:I25) -> 20236.045 | J26: =J21+SUM(J24:J25) -> 20289.39 | K26: =K21+SUM(K24:K25) -> 20333.26 | L26: =L21+SUM(L24:L25) -> 20265.484 | M26: =M21+SUM(M24:M25) -> 20187.371 | N26: =N21+SUM(N24:N25) -> 20193.422 | P26: ok
B28: Amortization
B29: Depreciation | F29: -2960 | G29: -3196 | H29: -3452 | I29: =I197*-1 -> -4962.9375 | J29: =J197*-1 -> -5412.9375 | K29: =K197*-1 -> -5837.9375 | L29: =L197*-1 -> -6187.9375 | M29: =M197*-1 -> -6437.9375 | N29: =N197*-1 -> -6712.9375
B30: EBIT | F30: =F26+F29 -> 15443.7 | G30: =G26+G29 -> 15410.851 | H30: =H26+H29 -> 16359.448 | I30: =I26+I29 -> 15273.107 | J30: =J26+J29 -> 14876.452 | K30: =K26+K29 -> 14495.322 | L30: =L26+L29 -> 14077.546 | M30: =M26+M29 -> 13749.434 | N30: =N26+N29 -> 13480.484
B32: Interest Expense | F32: -1688 | G32: -2200 | H32: -2350 | I32: =I295*-1 -> -1110 | J32: =J295*-1 -> -930 | K32: =K295*-1 -> -780 | L32: =L295*-1 -> -630 | M32: =M295*-1 -> -450 | N32: =N295*-1 -> -300
B33: Interest Income | F33: 200 | G33: 180 | H33: 193 | I33: =I296*-1 -> 84.099991 | J33: =J296*-1 -> 110.66679 | K33: =K296*-1 -> 160.91113 | L33: =L296*-1 -> 184.93386 | M33: =M296*-1 -> 240.31815 | N33: =N296*-1 -> 296.1942
B34: EBT | F34: =F30+F32+F33 -> 13955.7 | G34: =G30+G32+G33 -> 13390.851 | H34: =H30+H32+H33 -> 14202.448 | I34: =I30+I32+I33 -> 14247.207 | J34: =J30+J32+J33 -> 14057.119 | K34: =K30+K32+K33 -> 13876.233 | L34: =L30+L32+L33 -> 13632.48 | M34: =M30+M32+M33 -> 13539.752 | N34: =N30+N32+N33 -> 13476.678
B36: Current Tax | F36: 0 | G36: 0 | H36: 0 | I36: =I363 -> 0 | J36: =J363 -> 233.41219 | K36: =K363 -> 3125.0759 | L36: =L363 -> 3159.6576 | M36: =M363 -> 3280.7926 | N36: =N34*C17 -> 3369.1696
B37: Deferred Tax | F37: 3155 | G37: 2861 | H37: 3012 | I37: =I364 -> 3561.8019 | J37: =J364 -> 3280.8675 | K37: =K364 -> 343.98241 | L37: =L364 -> 248.46239 | M37: =M364 -> 104.14537 | N37: =N364 -> 0
B38: Total Tax | F38: =SUM(F36:F37) -> 3155 | G38: =SUM(G36:G37) -> 2861 | H38: =SUM(H36:H37) -> 3012 | I38: =SUM(I36:I37) -> 3561.8019 | J38: =SUM(J36:J37) -> 3514.2797 | K38: =SUM(K36:K37) -> 3469.0583 | L38: =SUM(L36:L37) -> 3408.12 | M38: =SUM(M36:M37) -> 3384.938 | N38: =SUM(N36:N37) -> 3369.1696
B40: Net Income | F40: =F34-F38 -> 10800.7 | G40: =G34-G38 -> 10529.851 | H40: =H34-H38 -> 11190.448 | I40: =I34-I38 -> 10685.406 | J40: =J34-J38 -> 10542.839 | K40: =K34-K38 -> 10407.175 | L40: =L34-L38 -> 10224.36 | M40: =M34-M38 -> 10154.814 | N40: =N34-N38 -> 10107.509
B44: Cash Flow Statement
B46: All figures in USD thousands unless stated | F46: =F$3 -> 2020 | G46: =G$3 -> 2021 | H46: =H$3 -> 2022 | I46: =I$3 -> 2023 | J46: =J$3 -> 2024 | K46: =K$3 -> 2025 | L46: =L$3 -> 2026 | M46: =M$3 -> 2027 | N46: =N$3 -> Term
B50: CASH FROM OPERATING
B51: Net Income | F51: =F40 -> 10800.7 | G51: =G40 -> 10529.851 | H51: =H40 -> 11190.448 | I51: =I40 -> 10685.406 | J51: =J40 -> 10542.839 | K51: =K40 -> 10407.175 | L51: =L40 -> 10224.36 | M51: =M40 -> 10154.814 | N51: =N40 -> 10107.509 | P51: ok
B52: Deferred Taxes | F52: =F37 -> 3155 | G52: =G37 -> 2861 | H52: =H37 -> 3012 | I52: =I37 -> 3561.8019 | J52: =J37 -> 3280.8675 | K52: =K37 -> 343.98241 | L52: =L37 -> 248.46239 | M52: =M37 -> 104.14537 | ... O52: =O37 -> 0 | P52: ok
B53: Depreciation | F53: =F29*-1 -> 2960 | G53: =G29*-1 -> 3196 | H53: =H29*-1 -> 3452 | I53: =I29*-1 -> 4962.9375 | J53: =J29*-1 -> 5412.9375 | K53: =K29*-1 -> 5837.9375 | L53: =L29*-1 -> 6187.9375 | M53: =M29*-1 -> 6437.9375 | N53: =N29*-1 -> 6712.9375 | P53: ok
B54: Cash From Accounts Receivable | F54: -600 | G54: =F140-G140 -> -625 | H54: =G140-H140 -> -291 | I54: =H140-I140 -> -202.8915 | J54: =I140-J140 -> -136.53783 | K54: =J140-K140 -> -139.26859 | L54: =K140-L140 -> -106.54047 | M54: =L140-M140 -> -108.13858 | N54: =M140-N140 -> -73.17377
B55: Cash From Inventory | F55: -400 | G55: =F141-G141 -> -131 | H55: =G141-H141 -> -86 | I55: =H141-I141 -> 181.48763 | J55: =I141-J141 -> -54.825371 | K55: =J141-K141 -> -56.470132 | L55: =K141-L141 -> -48.470197 | M55: =L141-M141 -> -49.681952 | N55: =M141-N141 -> -30.5544
B56: Cash From Accounts Payable | F56: -260 | G56: =G142-F142 -> 181 | H56: =H142-G142 -> 114 | I56: =I142-H142 -> -394.98021 | J56: =J142-I142 -> 87.720594 | K56: =K142-J142 -> 90.352211 | L56: =L142-K142 -> 77.552315 | M56: =M142-L142 -> 79.491123 | N56: =N142-M142 -> 48.88704
B57: Subtotal | F57: =SUM(F51:F56) -> 15655.7 | G57: =SUM(G51:G56) -> 16011.851 | H57: =SUM(H51:H56) -> 17391.448 | I57: =SUM(I51:I56) -> 18793.761 | J57: =SUM(J51:J56) -> 19133.002 | K57: =SUM(K51:K56) -> 16483.708 | L57: =SUM(L51:L56) -> 16583.301 | M57: =SUM(M51:M56) -> 16618.567 | N57: =SUM(N51:N56) -> 16765.605
B60: CASH FROM INVESTING
B61: Capital Expenditure | F61: =F163*-1 -> -9015 | G61: =G163*-1 -> -11733 | H61: =H163*-1 -> -11130 | I61: =I163*-1 -> -10000 | J61: =J163*-1 -> -8000 | K61: =K163*-1 -> -9000 | L61: =L163*-1 -> -5000 | M61: =M163*-1 -> -5000 | N61: =N163*-1 -> -6000 | P61: ok
B62: Subtotal | F62: =SUM(F61) -> -9015 | G62: =SUM(G61) -> -11733 | H62: =SUM(H61) -> -11130 | I62: =SUM(I61) -> -10000 | J62: =SUM(J61) -> -8000 | K62: =SUM(K61) -> -9000 | L62: =SUM(L61) -> -5000 | M62: =SUM(M61) -> -5000 | N62: =SUM(N61) -> -6000
B65: CASH FROM FINANCING
B66: Change in Long-Term Debt | F66: 0 | G66: -4000 | H66: -4000 | I66: =Inputs!G41 -> -3000 | J66: =Inputs!H41 -> -3000 | K66: =Inputs!I41 -> -2000 | L66: =Inputs!J41 -> -3000 | M66: =Inputs!K41 -> -3000 | N66: =Inputs!L41 -> -2000
B67: Change in Revolving Credit Line | F67: 0 | G67: 0 | H67: 0 | I67: =I287 -> 0 | J67: =J287 -> 0 | K67: =K287 -> 0 | L67: =L287 -> 0 | M67: =M287 -> 0 | N67: =N287 -> 0
B68: Change in Common Equity | F68: 0 | G68: 0 | H68: 0 | I68: =Inputs!G42 -> -1000 | J68: =Inputs!H42 -> -1000 | K68: =Inputs!I42 -> -1000 | L68: =Inputs!J42 -> -1000 | M68: =Inputs!K42 -> -1000 | N68: =Inputs!L42 -> -1000
B69: Dividends | F69: -3465 | G69: -3761 | H69: -3216 | I69: =I317*-1 -> -2137.0811 | J69: =J317*-1 -> -2108.5678 | K69: =K317*-1 -> -2081.435 | L69: =L317*-1 -> -2044.872 | M69: =M317*-1 -> -2030.9628 | N69: =N317*-1 -> -2021.5017
B70: Subtotal | F70: =SUM(F66:F69) -> -3465 | G70: =SUM(G66:G69) -> -7761 | H70: =SUM(H66:H69) -> -7216 | I70: =SUM(I66:I69) -> -6137.0811 | J70: =SUM(J66:J69) -> -6108.5678 | K70: =SUM(K66:K69) -> -5081.435 | L70: =SUM(L66:L69) -> -6044.872 | M70: =SUM(M66:M69) -> -6030.9628 | N70: =SUM(N66:N69) -> -5021.5017
B73: CASH BALANCE
B74: Beginning of the Year | F74: 9671 | G74: =F76 -> 12846.7 | H74: =G76 -> 9364.5506 | I74: =H76 -> 8409.9991 | J74: =I76 -> 11066.679 | K74: =J76 -> 16091.113 | L74: =K76 -> 18493.386 | M74: =L76 -> 24031.815 | N74: =M76 -> 29619.42
B75: Increase / (Decrease) | F75: =F57+F62+F70 -> 3175.7 | G75: =G57+G62+G70 -> -3482.1494 | H75: =H57+H62+H70 -> -954.5515 | I75: =I57+I62+I70 -> 2656.6797 | J75: =J57+J62+J70 -> 5024.4337 | K75: =K57+K62+K70 -> 2402.2734 | L75: =L57+L62+L70 -> 5538.4295 | M75: =M57+M62+M70 -> 5587.6046 | N75: =N57+N62+N70 -> 5744.1033
B76: End of the Year | F76: =SUM(F74:F75) -> 12846.7 | G76: =SUM(G74:G75) -> 9364.5506 | H76: =SUM(H74:H75) -> 8409.9991 | I76: =SUM(I74:I75) -> 11066.679 | J76: =SUM(J74:J75) -> 16091.113 | K76: =SUM(K74:K75) -> 18493.386 | L76: =SUM(L74:L75) -> 24031.815 | M76: =SUM(M74:M75) -> 29619.42 | N76: =SUM(N74:N75) -> 35363.523
B80: Balance Sheet
B82: All figures in USD thousands unless stated | F82: =F$3 -> 2020 | G82: =G$3 -> 2021 | H82: =H$3 -> 2022 | I82: =I$3 -> 2023 | J82: =J$3 -> 2024 | K82: =K$3 -> 2025 | L82: =L$3 -> 2026 | M82: =M$3 -> 2027 | N82: =N$3 -> Term
B85: ASSETS
B87: Cash | F87: =F76 -> 12846.7 | G87: =G76 -> 9364.5506 | H87: =H76 -> 8409.9991 | I87: =I76 -> 11066.679 | J87: =J76 -> 16091.113 | K87: =K76 -> 18493.386 | L87: =L76 -> 24031.815 | M87: =M76 -> 29619.42 | N87: =N76 -> 35363.523 | P87: ok
B88: Accounts Receivable | F88: =F140 -> 5708 | G88: =G140 -> 6333 | H88: =H140 -> 6624 | I88: =I140 -> 6826.8915 | J88: =J140 -> 6963.4293 | K88: =K140 -> 7102.6979 | L88: =L140 -> 7209.2384 | M88: =M140 -> 7317.377 | N88: =N140 -> 7390.5507 | P88: ok
B89: Inventories | F89: =F141 -> 1792 | G89: =G141 -> 1923 | H89: =H141 -> 2009 | I89: =I141 -> 1827.5124 | J89: =J141 -> 1882.3377 | K89: =K141 -> 1938.8079 | L89: =L141 -> 1987.2781 | M89: =M141 -> 2036.96 | N89: =N141 -> 2067.5144 | P89: ok
B90: Total Current Assets | F90: =SUM(F87:F89) -> 20346.7 | G90: =SUM(G87:G89) -> 17620.551 | H90: =SUM(H87:H89) -> 17042.999 | I90: =SUM(I87:I89) -> 19721.083 | J90: =SUM(J87:J89) -> 24936.88 | K90: =SUM(K87:K89) -> 27534.892 | L90: =SUM(L87:L89) -> 33228.332 | M90: =SUM(M87:M89) -> 38973.757 | N90: =SUM(N87:N89) -> 44821.589 | P90: ok
B92: Property Plant & Equipment | F92: 59192 | G92: 67729 | H92: =Inputs!L103 -> 75407 | I92: =I220 -> 80444.062 | J92: =J220 -> 83031.125 | K92: =K220 -> 86193.188 | L92: =L220 -> 85005.25 | M92: =M220 -> 83567.312 | N92: =N220 -> 82854.375 | P92: ok
B95: Total Assets | F95: =SUM(F90:F92) -> 79538.7 | G95: =SUM(G90:G92) -> 85349.551 | H95: =SUM(H90:H92) -> 92449.999 | I95: =SUM(I90:I92) -> 100165.15 | J95: =SUM(J90:J92) -> 107968 | K95: =SUM(K90:K92) -> 113728.08 | L95: =SUM(L90:L92) -> 118233.58 | M95: =SUM(M90:M92) -> 122541.07 | N95: =SUM(N90:N92) -> 127675.96 | P95: ok
B98: LIABILITIES
B100: Accounts Payable | F100: =F142 -> 3024 | G100: =G142 -> 3205 | H100: =H142 -> 3319 | I100: =I142 -> 2924.0198 | J100: =J142 -> 3011.7404 | K100: =K142 -> 3102.0926 | L100: =L142 -> 3179.6449 | M100: =M142 -> 3259.136 | N100: =N142 -> 3308.0231 | P100: ok
B101: Revolving Credit Line | F101: 0 | G101: 0 | H101: 0 | I101: =I288 -> 0 | J101: =J288 -> 0 | K101: =K288 -> 0 | L101: =L288 -> 0 | M101: =M288 -> 0 | N101: =N288 -> 0
B102: Total Current Liabilities | F102: =SUM(F100:F101) -> 3024 | G102: =SUM(G100:G101) -> 3205 | H102: =SUM(H100:H101) -> 3319 | I102: =SUM(I100:I101) -> 2924.0198 | J102: =SUM(J100:J101) -> 3011.7404 | K102: =SUM(K100:K101) -> 3102.0926 | L102: =SUM(L100:L101) -> 3179.6449 | M102: =SUM(M100:M101) -> 3259.136 | N102: =SUM(N100:N101) -> 3308.0231 | P102: ok
B104: Deferred Taxes | F104: 4155 | G104: 7016 | H104: 10028 | I104: =H104+I52 -> 13589.802 | J104: =I104+J52 -> 16870.669 | K104: =J104+K52 -> 17214.652 | L104: =K104+L52 -> 17463.114 | M104: =L104+M52 -> 17567.26 | N104: =M104+N52 -> 17567.26 | O104: ='[1]Model-R'!R104 -> 0
B105: Long-Term Debt | F105: 28000 | G105: 24000 | H105: 20000 | I105: =I256 -> 17000 | J105: =J256 -> 14000 | K105: =K256 -> 12000 | L105: =L256 -> 9000 | M105: =M256 -> 6000 | N105: =N256 -> 4000 | P105: ok
B106: Total Liabilities | F106: =SUM(F102:F105) -> 35179 | G106: =SUM(G102:G105) -> 34221 | H106: =SUM(H102:H105) -> 33347 | I106: =SUM(I102:I105) -> 33513.822 | J106: =SUM(J102:J105) -> 33882.41 | K106: =SUM(K102:K105) -> 32316.744 | L106: =SUM(L102:L105) -> 29642.759 | M106: =SUM(M102:M105) -> 26826.396 | N106: =SUM(N102:N105) -> 24875.283 | P106: ok
B109: EQUITY
B111: Common Equity | F111: 38669.7 | G111: 38669.7 | H111: 38669.7 | I111: =I313 -> 37669.7 | J111: =J313 -> 36669.7 | K111: =K313 -> 35669.7 | L111: =L313 -> 34669.7 | M111: =M313 -> 33669.7 | N111: =N313 -> 32669.7 | P111: ok
B112: Retained Earnings | F112: 5690 | G112: 12458.851 | H112: 20433.299 | I112: =I327 -> 28981.624 | J112: =J327 -> 37415.895 | K112: =K327 -> 45741.635 | L112: =L327 -> 53921.123 | M112: =M327 -> 62044.974 | N112: =N327 -> 70130.981 | P112: ok
B113: Total Shareholders' Equity | F113: =SUM(F111:F112) -> 44359.7 | G113: =SUM(G111:G112) -> 51128.551 | H113: =SUM(H111:H112) -> 59102.999 | I113: =SUM(I111:I112) -> 66651.324 | J113: =SUM(J111:J112) -> 74085.595 | K113: =SUM(K111:K112) -> 81411.335 | L113: =SUM(L111:L112) -> 88590.823 | M113: =SUM(M111:M112) -> 95714.674 | N113: =SUM(N111:N112) -> 102800.68 | P113: ok
B116: Total Liabilities & Equity | F116: =F113+F106 -> 79538.7 | G116: =G113+G106 -> 85349.551 | H116: =H113+H106 -> 92449.999 | I116: =I113+I106 -> 100165.15 | J116: =J113+J106 -> 107968 | K116: =K113+K106 -> 113728.08 | L116: =L113+L106 -> 118233.58 | M116: =M113+M106 -> 122541.07 | N116: =N113+N106 -> 127675.96
B119: Check | F119: =ROUND(F116-F95,0) -> 0 | G119: =ROUND(G116-G95,0) -> 0 | H119: =ROUND(H116-H95,0) -> 0 | I119: =ROUND(I116-I95,0) -> 0 | J119: =ROUND(J116-J95,0) -> 0 | K119: =ROUND(K116-K95,0) -> 0 | L119: =ROUND(L116-L95,0) -> 0 | M119: =ROUND(M116-M95,0) -> 0 | N119: =ROUND(N116-N95,0) -> 0
B123: Working Capital Schedule
B125: All figures in USD thousands unless stated | F125: =F$3 -> 2020 | G125: =G$3 -> 2021 | H125: =H$3 -> 2022 | I125: =I$3 -> 2023 | J125: =J$3 -> 2024 | K125: =K$3 -> 2025 | L125: =L$3 -> 2026 | M125: =M$3 -> 2027 | N125: =N$3 -> Term
B126: =$B$4 -> Model Running: Base Case Drivers
B128: Days in Period | F128: =F$6 -> 365 | G128: =G$6 -> 365 | H128: =H$6 -> 365 | I128: =I$6 -> 365 | J128: =J$6 -> 365 | K128: =K$6 -> 365 | L128: =L$6 -> 365 | M128: =M$6 -> 365 | N128: =N$6 -> 365 | P128: ok
B129: Revenue | F129: =F19 -> 50589 | G129: =G19 -> 51647.865 | H129: =H19 -> 53760.85 | I129: =I19 -> 55373.675 | J129: =J19 -> 56481.149 | K129: =K19 -> 57610.772 | L129: =L19 -> 58474.934 | M129: =M19 -> 59352.058 | N129: =N19 -> 59945.578 | P129: ok
B130: COGS | F130: =F20*-1 -> 24544.3 | G130: =G20*-1 -> 25104.014 | H130: =H20*-1 -> 25779.401 | I130: =I20*-1 -> 26681.681 | J130: =J20*-1 -> 27482.131 | K130: =K20*-1 -> 28306.595 | L130: =L20*-1 -> 29014.26 | M130: =M20*-1 -> 29739.616 | N130: =N20*-1 -> 30185.711 | P130: ok
B133: AMOUNTS PER DAY 1
B134: Accounts Receivable | D134: (Days) | F134: =(F140/F129)*F$128 -> 41.183261 | G134: =(G140/G129)*G$128 -> 44.755867 | H134: =(H140/H129)*H$128 -> 44.972503 | I134: =Inputs!G35 -> 45 | J134: =Inputs!H35 -> 45 | K134: =Inputs!I35 -> 45 | L134: =Inputs!J35 -> 45 | M134: =Inputs!K35 -> 45 | N134: =Inputs!L35 -> 45 | P134: ok
B135: Inventory | D135: (Days) | F135: =(F141/F130)*F$128 -> 26.648957 | G135: =(G141/G130)*G$128 -> 27.959472 | H135: =(H141/H130)*H$128 -> 28.444609 | I135: =Inputs!G36 -> 25 | J135: =Inputs!H36 -> 25 | K135: =Inputs!I36 -> 25 | L135: =Inputs!J36 -> 25 | M135: =Inputs!K36 -> 25 | N135: =Inputs!L36 -> 25 | P135: ok
B136: Accounts Payable | D136: (Days) | F136: =(F142/F130)*F$128 -> 44.970115 | G136: =(G142/G130)*G$128 -> 46.599121 | H136: =(H142/H130)*H$128 -> 46.992363 | I136: =Inputs!G37 -> 40 | J136: =Inputs!H37 -> 40 | K136: =Inputs!I37 -> 40 | L136: =Inputs!J37 -> 40 | M136: =Inputs!K37 -> 40 | N136: =Inputs!L37 -> 40 | P136: ok
B139: TOTAL AMOUNTS
B140: Accounts Receivable | F140: 5708 | G140: 6333 | H140: 6624 | I140: =(I134/I$128)*I129 -> 6826.8915 | J140: =(J134/J$128)*J129 -> 6963.4293 | K140: =(K134/K$128)*K129 -> 7102.6979 | L140: =(L134/L$128)*L129 -> 7209.2384 | M140: =(M134/M$128)*M129 -> 7317.377 | N140: =(N134/N$128)*N129 -> 7390.5507 | P140: ok
B141: Inventory | F141: 1792 | G141: 1923 | H141: 2009 | I141: =(I135/I$128)*I130 -> 1827.5124 | J141: =(J135/J$128)*J130 -> 1882.3377 | K141: =(K135/K$128)*K130 -> 1938.8079 | L141: =(L135/L$128)*L130 -> 1987.2781 | M141: =(M135/M$128)*M130 -> 2036.96 | N141: =(N135/N$128)*N130 -> 2067.5144 | P141: ok
B142: Accounts Payable | F142: 3024 | G142: 3205 | H142: 3319 | I142: =(I136/I$128)*I130 -> 2924.0198 | J142: =(J136/J$128)*J130 -> 3011.7404 | K142: =(K136/K$128)*K130 -> 3102.0926 | L142: =(L136/L$128)*L130 -> 3179.6449 | M142: =(M136/M$128)*M130 -> 3259.136 | N142: =(N136/N$128)*N130 -> 3308.0231 | P142: ok
B145: NET WORKING CAPITAL
B146: Current Assets | F146: =SUM(F140:F141) -> 7500 | G146: =SUM(G140:G141) -> 8256 | H146: =SUM(H140:H141) -> 8633 | I146: =SUM(I140:I141) -> 8654.4039 | J146: =SUM(J140:J141) -> 8845.7671 | K146: =SUM(K140:K141) -> 9041.5058 | L146: =SUM(L140:L141) -> 9196.5165 | M146: =SUM(M140:M141) -> 9354.337 | N146: =SUM(N140:N141) -> 9458.0651 | P146: ok
B147: Current Liabilities | F147: =SUM(F142) -> 3024 | G147: =SUM(G142) -> 3205 | H147: =SUM(H142) -> 3319 | I147: =SUM(I142) -> 2924.0198 | J147: =SUM(J142) -> 3011.7404 | K147: =SUM(K142) -> 3102.0926 | L147: =SUM(L142) -> 3179.6449 | M147: =SUM(M142) -> 3259.136 | N147: =SUM(N142) -> 3308.0231 | P147: ok
B148: Net Working Capital | F148: =F146-F147 -> 4476 | G148: =G146-G147 -> 5051 | H148: =H146-H147 -> 5314 | I148: =I146-I147 -> 5730.3841 | J148: =J146-J147 -> 5834.0267 | K148: =K146-K147 -> 5939.4132 | L148: =L146-L147 -> 6016.8715 | M148: =M146-M147 -> 6095.201 | N148: =N146-N147 -> 6150.0421 | P148: ok
B151: Cash from Working Capital Items | F151: ='Model-R'!S155 -> COMPLETE | G151: =F148-G148 -> -575 | H151: =G148-H148 -> -263 | I151: =H148-I148 -> -416.38408 | J151: =I148-J148 -> -103.64261 | K151: =J148-K148 -> -105.38651 | L151: =K148-L148 -> -77.458351 | M151: =L148-M148 -> -78.329405 | N151: =M148-N148 -> -54.841129 | P151: ok
N154: We have assumed working capital amounts per day in terminal year are equal to the previous year.
B158: Depreciation Schedule
B160: All figures in USD thousands unless stated | F160: =F$3 -> 2020 | G160: =G$3 -> 2021 | H160: =H$3 -> 2022 | I160: =I$3 -> 2023 | J160: =J$3 -> 2024 | K160: =K$3 -> 2025 | L160: =L$3 -> 2026 | M160: =M$3 -> 2027 | N160: =N$3 -> Term
B161: =$B$4 -> Model Running: Base Case Drivers
B163: Capital Expenditure | F163: 9015 | G163: 11733 | H163: 11130 | I163: =Inputs!G24 -> 10000 | J163: =Inputs!H24 -> 8000 | K163: =Inputs!I24 -> 9000 | L163: =Inputs!J24 -> 5000 | M163: =Inputs!K24 -> 5000 | N163: =Inputs!L24 -> 6000 | P163: ok
B166: EXISTING ASSET DEPRECIATION 1 | D166: Years | I166: Percent of Full Year
B167: Useful Life: Existing Assets | D167: =Inputs!$L$115 -> 16 | I167: 1 | J167: =I167+1 -> 2 | K167: =J167+1 -> 3 | L167: =K167+1 -> 4 | M167: =L167+1 -> 5 | N167: term
B168: =CONCATENATE("PP&E at End of ",H160) -> PP&E at End of 2022 | D168: =Inputs!$L$103 -> 75407 | I168: =MIN($D167-SUM($H168:H168),1) -> 1 | J168: =MIN($D167-SUM($H168:I168),1) -> 1 | K168: =MIN($D167-SUM($H168:J168),1) -> 1 | L168: =MIN($D167-SUM($H168:K168),1) -> 1 | M168: =MIN($D167-SUM($H168:L168),1) -> 1 | N168: =MIN($D167-SUM($H168:M168),1) -> 1 | P168: ok
B172: NEW ASSET DEPRECIATION 1 | D172: Years | I172: Percent of Full Year
B173: Useful Life: New Assets | D173: =Inputs!$L$116 -> 20 | I173: 1 | J173: =I173+1 -> 2 | K173: =J173+1 -> 3 | L173: =K173+1 -> 4 | M173: =L173+1 -> 5 | N173: term
B174: First Year Accounting Depreciation | D174: =Inputs!$L$114 -> 0.5 | I174: =IF(H174="",$D$174,MIN($D173-SUM($H174:H174),1)) -> 0.5 | J174: =IF(I174="",$D$174,MIN($D173-SUM($H174:I174),1)) -> 1 | K174: =IF(J174="",$D$174,MIN($D173-SUM($H174:J174),1)) -> 1 | L174: =IF(K174="",$D$174,MIN($D173-SUM($H174:K174),1)) -> 1 | M174: =IF(L174="",$D$174,MIN($D173-SUM($H174:L174),1)) -> 1 | N174: =IF(M174="",$D$174,MIN($D173-SUM($H174:M174),1)) -> 1 | P174: ok
...

Sheet Outputs
B3: Dashboard: Perpetuity Method
D6: Model Drivers Set To | F6: 2 | L6: All figures in USD thousands unless stated
D9: Main Outputs 1 | L9: Selected Inputs
F11: Enterprise | G11: Equity | H11: Equity
F12: Value | G12: Value | H12: Per Share | L12: Terminal Growth Rate | O12: =Inputs!$F$115 -> 0.01
E13: ='Outputs-R'!Y11 -> 1 | F13: =Model!H488 -> 125713.01 | L13: WACC | O13: =Inputs!$L$92 -> 0.095866057
D14: Best Case | E14: 1 | F14: 176515.71 | G14: =F14-$O$14 -> 157873.71 | H14: =G14/$O$15 -> 4.6161905 | L14: Net Debt | N14: =CONCATENATE("(End of ",Model!$H$3,")") -> (End of 2022) | O14: =Inputs!$L$102 -> 18642
D15: Base Case | E15: 2 | F15: 125713.01 | G15: =F15-$O$14 -> 107071.01 | H15: =G15/$O$15 -> 3.1307312 | L15: Shares Outstanding | N15: (FD 000) | O15: =Inputs!$F$113 -> 34200
D16: Worst Case | E16: 3 | F16: 86963.94 | G16: =F16-$O$14 -> 68321.94 | H16: =G16/$O$15 -> 1.9977176 | L16: Current Stock Price | N16: (US$/sh) | O16: =Inputs!$F$114 -> 2.23
E17: ='Outputs-R'!U18 -> 1 | F17: ='Outputs-R'!Y18 -> 0 | G17: ='Outputs-R'!AC18 -> 1 | H17: ='Outputs-R'!AG18 -> 1
D20: Enterprise Value 1 | L20: Equity Value per Share
D22: Terminal Growth Rate | L22: Terminal Growth Rate
B23: ='Outputs-R'!U21 -> 1 | C23: =Model!H488 -> 125713.01 | D23: =E23-0.005 -> 0 | E23: =F23-0.005 -> 0.005 | F23: =Inputs!$F$115 -> 0.01 | G23: =F23+0.005 -> 0.015 | H23: =G23+0.005 -> 0.02 | L23: =D23 -> 0 | M23: =E23 -> 0.005 | N23: =F23 -> 0.01 | O23: =G23 -> 0.015 | P23: =H23 -> 0.02
B24: WACC | C24: =C25-0.01 -> 0.075866057 | D24: 125713.01 | E24: 125713.01 | F24: 125713.01 | G24: 125713.01 | H24: 125713.01 | J24: WACC | K24: =C24 -> 0.075866057 | L24: =D37/$O$15 -> 3.1307312 | M24: =E37/$O$15 -> 3.1307312 | N24: =F37/$O$15 -> 3.1307312 | O24: =G37/$O$15 -> 3.1307312 | P24: =H37/$O$15 -> 3.1307312
C25: =C26-0.01 -> 0.085866057 | D25: 125713.01 | E25: 125713.01 | F25: 125713.01 | G25: 125713.01 | H25: 125713.01 | K25: =C25 -> 0.085866057 | L25: =D38/$O$15 -> 3.1307312 | M25: =E38/$O$15 -> 3.1307312 | N25: =F38/$O$15 -> 3.1307312 | O25: =G38/$O$15 -> 3.1307312 | P25: =H38/$O$15 -> 3.1307312
C26: =Inputs!$L$92 -> 0.095866057 | D26: 125713.01 | E26: 125713.01 | F26: 125713.01 | G26: 125713.01 | H26: 125713.01 | K26: =C26 -> 0.095866057 | L26: =D39/$O$15 -> 3.1307312 | M26: =E39/$O$15 -> 3.1307312 | N26: =F39/$O$15 -> 3.1307312 | O26: =G39/$O$15 -> 3.1307312 | P26: =H39/$O$15 -> 3.1307312
C27: =C26+0.01 -> 0.10586606 | D27: 125713.01 | E27: 125713.01 | F27: 125713.01 | G27: 125713.01 | H27: 125713.01 | K27: =C27 -> 0.10586606 | L27: =D40/$O$15 -> 3.1307312 | M27: =E40/$O$15 -> 3.1307312 | N27: =F40/$O$15 -> 3.1307312 | O27: =G40/$O$15 -> 3.1307312 | P27: =H40/$O$15 -> 3.1307312
C28: =C27+0.01 -> 0.11586606 | D28: 125713.01 | E28: 125713.01 | F28: 125713.01 | G28: 125713.01 | H28: 125713.01 | K28: =C28 -> 0.11586606 | L28: =D41/$O$15 -> 3.1307312 | M28: =E41/$O$15 -> 3.1307312 | N28: =F41/$O$15 -> 3.1307312 | O28: =G41/$O$15 -> 3.1307312 | P28: =H41/$O$15 -> 3.1307312
H29: ='Outputs-R'!AE30 -> 1 | P29: ='Outputs-R'!Y37 -> 1
D33: Equity Value | L33: Premium (Discount) to Stock Price
D35: Terminal Growth Rate | L35: Terminal Growth Rate
D36: =D23 -> 0 | E36: =E23 -> 0.005 | F36: =F23 -> 0.01 | G36: =G23 -> 0.015 | H36: =H23 -> 0.02 | L36: =D36 -> 0 | M36: =E36 -> 0.005 | N36: =F36 -> 0.01 | O36: =G36 -> 0.015 | P36: =H36 -> 0.02
B37: WACC | C37: =C24 -> 0.075866057 | D37: =D24-$O$14 -> 107071.01 | E37: =E24-$O$14 -> 107071.01 | F37: =F24-$O$14 -> 107071.01 | G37: =G24-$O$14 -> 107071.01 | H37: =H24-$O$14 -> 107071.01 | J37: WACC | K37: =C37 -> 0.075866057 | L37: =L24/$O$16-1 -> 0.40391535 | M37: =M24/$O$16-1 -> 0.40391535 | N37: =N24/$O$16-1 -> 0.40391535 | O37: =O24/$O$16-1 -> 0.40391535 | P37: =P24/$O$16-1 -> 0.40391535
C38: =C25 -> 0.085866057 | D38: =D25-$O$14 -> 107071.01 | E38: =E25-$O$14 -> 107071.01 | F38: =F25-$O$14 -> 107071.01 | G38: =G25-$O$14 -> 107071.01 | H38: =H25-$O$14 -> 107071.01 | K38: =C38 -> 0.085866057 | L38: =L25/$O$16-1 -> 0.40391535 | M38: =M25/$O$16-1 -> 0.40391535 | N38: =N25/$O$16-1 -> 0.40391535 | O38: =O25/$O$16-1 -> 0.40391535 | P38: =P25/$O$16-1 -> 0.40391535
C39: =C26 -> 0.095866057 | D39: =D26-$O$14 -> 107071.01 | E39: =E26-$O$14 -> 107071.01 | F39: =F26-$O$14 -> 107071.01 | G39: =G26-$O$14 -> 107071.01 | H39: =H26-$O$14 -> 107071.01 | K39: =C39 -> 0.095866057 | L39: =L26/$O$16-1 -> 0.40391535 | M39: =M26/$O$16-1 -> 0.40391535 | N39: =N26/$O$16-1 -> 0.40391535 | O39: =O26/$O$16-1 -> 0.40391535 | P39: =P26/$O$16-1 -> 0.40391535
C40: =C27 -> 0.10586606 | D40: =D27-$O$14 -> 107071.01 | E40: =E27-$O$14 -> 107071.01 | F40: =F27-$O$14 -> 107071.01 | G40: =G27-$O$14 -> 107071.01 | H40: =H27-$O$14 -> 107071.01 | K40: =C40 -> 0.10586606 | L40: =L27/$O$16-1 -> 0.40391535 | M40: =M27/$O$16-1 -> 0.40391535 | N40: =N27/$O$16-1 -> 0.40391535 | O40: =O27/$O$16-1 -> 0.40391535 | P40: =P27/$O$16-1 -> 0.40391535
C41: =C28 -> 0.11586606 | D41: =D28-$O$14 -> 107071.01 | E41: =E28-$O$14 -> 107071.01 | F41: =F28-$O$14 -> 107071.01 | G41: =G28-$O$14 -> 107071.01 | H41: =H28-$O$14 -> 107071.01 | K41: =C41 -> 0.11586606 | L41: =L28/$O$16-1 -> 0.40391535 | M41: =M28/$O$16-1 -> 0.40391535 | N41: =N28/$O$16-1 -> 0.40391535 | O41: =O28/$O$16-1 -> 0.40391535 | P41: =P28/$O$16-1 -> 0.40391535
H42: ='Outputs-R'!U40 -> 1 | P42: ='Outputs-R'!Y40 -> 1
D43: ='Outputs-R'!S43 | P43: These tables require the workbook calculation to be set to automatic to update.
B47: Dashboard: Multiple Method
D50: Model Drivers Set To | F50: =F6 -> 2 | L50: All figures in USD thousands unless stated
D53: Main Outputs 1 | L53: Selected Inputs
F55: Enterprise | G55: Equity | H55: Equity
F56: Value | G56: Value | H56: Per Share | L56: Terminal Multiple | O56: =+Inputs!$F$116 -> 7
E57: ='Outputs-R'!Y55 -> 1 | F57: =Model!H535 -> 130862.76 | L57: WACC | O57: =Inputs!$L$92 -> 0.095866057
D58: =D14 -> Best Case | E58: 1 | F58: 163673.86 | G58: =F58-$O$58 -> 145031.86 | H58: =+G58/$O$59 -> 4.2406978 | L58: Net Debt | N58: =N14 -> (End of 2022) | O58: =Inputs!$L$102 -> 18642
D59: =D15 -> Base Case | E59: 2 | F59: 130862.76 | G59: =F59-$O$58 -> 112220.76 | H59: =+G59/$O$59 -> 3.2813089 | L59: Shares Outstanding | N59: (FD 000) | O59: =Inputs!$F$113 -> 34200
D60: =D16 -> Worst Case | E60: 3 | F60: 101841.48 | G60: =F60-$O$58 -> 83199.483 | H60: =+G60/$O$59 -> 2.4327334 | L60: Current Stock Price | N60: (US$/sh) | O60: =Inputs!$F$114 -> 2.23
E61: ='Outputs-R'!U58 -> 1 | F61: ='Outputs-R'!Y62 -> 0
D64: Enterprise Value 1 | L64: Equity Value per Share
D66: Terminal Multiple | L66: Terminal Multiple
B67: ='Outputs-R'!U65 -> 1 | C67: =Model!H535 -> 130862.76 | D67: =E67-0.5 -> 6 | E67: =F67-0.5 -> 6.5 | F67: =+Inputs!$F$116 -> 7 | G67: =+F67+0.5 -> 7.5 | H67: =+G67+0.5 -> 8 | L67: =D67 -> 6 | M67: =E67 -> 6.5 | N67: =F67 -> 7 | O67: =G67 -> 7.5 | P67: =H67 -> 8
B68: WACC | C68: =C69-0.01 -> 0.075866057 | D68: 130862.76 | E68: 130862.76 | F68: 130862.76 | G68: 130862.76 | H68: 130862.76 | J68: WACC | K68: =C68 -> 0.075866057 | L68: =D81/$O$59 -> 3.2813089 | M68: =E81/$O$59 -> 3.2813089 | N68: =F81/$O$59 -> 3.2813089 | O68: =G81/$O$59 -> 3.2813089 | P68: =H81/$O$59 -> 3.2813089
C69: =C70-0.01 -> 0.085866057 | D69: 130862.76 | E69: 130862.76 | F69: 130862.76 | G69: 130862.76 | H69: 130862.76 | K69: =C69 -> 0.085866057 | L69: =D82/$O$59 -> 3.2813089 | M69: =E82/$O$59 -> 3.2813089 | N69: =F82/$O$59 -> 3.2813089 | O69: =G82/$O$59 -> 3.2813089 | P69: =H82/$O$59 -> 3.2813089
C70: =Inputs!$L$92 -> 0.095866057 | D70: 130862.76 | E70: 130862.76 | F70: 130862.76 | G70: 130862.76 | H70: 130862.76 | K70: =C70 -> 0.095866057 | L70: =D83/$O$59 -> 3.2813089 | M70: =E83/$O$59 -> 3.2813089 | N70: =F83/$O$59 -> 3.2813089 | O70: =G83/$O$59 -> 3.2813089 | P70: =H83/$O$59 -> 3.2813089
C71: =C70+0.01 -> 0.10586606 | D71: 130862.76 | E71: 130862.76 | F71: 130862.76 | G71: 130862.76 | H71: 130862.76 | K71: =C71 -> 0.10586606 | L71: =D84/$O$59 -> 3.2813089 | M71: =E84/$O$59 -> 3.2813089 | N71: =F84/$O$59 -> 3.2813089 | O71: =G84/$O$59 -> 3.2813089 | P71: =H84/$O$59 -> 3.2813089
C72: =C71+0.01 -> 0.11586606 | D72: 130862.76 | E72: 130862.76 | F72: 130862.76 | G72: 130862.76 | H72: 130862.76 | K72: =C72 -> 0.11586606 | L72: =D85/$O$59 -> 3.2813089 | M72: =E85/$O$59 -> 3.2813089 | N72: =F85/$O$59 -> 3.2813089 | O72: =G85/$O$59 -> 3.2813089 | P72: =H85/$O$59 -> 3.2813089
H73: ='Outputs-R'!AE74 -> 1
D77: Equity Value | L77: Premium (Discount) to Stock Price
D79: Terminal Multiple | L79: Terminal Multiple
D80: =D67 -> 6 | E80: =E67 -> 6.5 | F80: =F67 -> 7 | G80: =G67 -> 7.5 | H80: =H67 -> 8 | L80: =D80 -> 6 | M80: =E80 -> 6.5 | N80: =F80 -> 7 | O80: =G80 -> 7.5 | P80: =H80 -> 8
B81: WACC | C81: =C68 -> 0.075866057 | D81: =D68-$O$58 -> 112220.76 | E81: =E68-$O$58 -> 112220.76 | F81: =F68-$O$58 -> 112220.76 | G81: =G68-$O$58 -> 112220.76 | H81: =H68-$O$58 -> 112220.76 | J81: WACC | K81: =C81 -> 0.075866057 | L81: =L68/$O$60-1 -> 0.47143897 | M81: =M68/$O$60-1 -> 0.47143897 | N81: =N68/$O$60-1 -> 0.47143897 | O81: =O68/$O$60-1 -> 0.47143897 | P81: =P68/$O$60-1 -> 0.47143897
C82: =C69 -> 0.085866057 | D82: =D69-$O$58 -> 112220.76 | E82: =E69-$O$58 -> 112220.76 | F82: =F69-$O$58 -> 112220.76 | G82: =G69-$O$58 -> 112220.76 | H82: =H69-$O$58 -> 112220.76 | K82: =C82 -> 0.085866057 | L82: =L69/$O$60-1 -> 0.47143897 | M82: =M69/$O$60-1 -> 0.47143897 | N82: =N69/$O$60-1 -> 0.47143897 | O82: =O69/$O$60-1 -> 0.47143897 | P82: =P69/$O$60-1 -> 0.47143897
C83: =C70 -> 0.095866057 | D83: =D70-$O$58 -> 112220.76 | E83: =E70-$O$58 -> 112220.76 | F83: =F70-$O$58 -> 112220.76 | G83: =G70-$O$58 -> 112220.76 | H83: =H70-$O$58 -> 112220.76 | K83: =C83 -> 0.095866057 | L83: =L70/$O$60-1 -> 0.47143897 | M83: =M70/$O$60-1 -> 0.47143897 | N83: =N70/$O$60-1 -> 0.47143897 | O83: =O70/$O$60-1 -> 0.47143897 | P83: =P70/$O$60-1 -> 0.47143897
C84: =C71 -> 0.10586606 | D84: =D71-$O$58 -> 112220.76 | E84: =E71-$O$58 -> 112220.76 | F84: =F71-$O$58 -> 112220.76 | G84: =G71-$O$58 -> 112220.76 | H84: =H71-$O$58 -> 112220.76 | K84: =C84 -> 0.10586606 | L84: =L71/$O$60-1 -> 0.47143897 | M84: =M71/$O$60-1 -> 0.47143897 | N84: =N71/$O$60-1 -> 0.47143897 | O84: =O71/$O$60-1 -> 0.47143897 | P84: =P71/$O$60-1 -> 0.47143897
C85: =C72 -> 0.11586606 | D85: =D72-$O$58 -> 112220.76 | E85: =E72-$O$58 -> 112220.76 | F85: =F72-$O$58 -> 112220.76 | G85: =G72-$O$58 -> 112220.76 | H85: =H72-$O$58 -> 112220.76 | K85: =C85 -> 0.11586606 | L85: =L72/$O$60-1 -> 0.47143897 | M85: =M72/$O$60-1 -> 0.47143897 | N85: =N72/$O$60-1 -> 0.47143897 | O85: =O72/$O$60-1 -> 0.47143897 | P85: =P72/$O$60-1 -> 0.47143897
D87: ='Outputs-R'!S87 | P87: These tables require the workbook calculation to be set to automatic to update.

Sheet Relative Valuation
B3: Relative Valuation - Using Comparable Company Analysis
B5: All figures in USD thousands unless stated
E8: Share | F8: Shares | G8: Market | H8: Net | I8: Enterprise | J8: EBITDA | L8: Net Income | N8: EV / EBITDA | P8: P / E 2
B9: Peer Companies | C9: Industry | D9: Location | E9: Price | F9: Outstand. | G9: Cap | H9: Debt | I9: Value 1 | J9: 2022 | K9: 2023 | L9: 2022 | M9: 2023 | N9: 2022 | O9: 2023 | P9: 2022 | Q9: 2023
E10: $ | F10: mm | N10: x | O10: x | P10: x | Q10: x
B11: =Inputs!B54 -> Peer 1 | C11: =Inputs!C54 -> Industry 1 | D11: =Inputs!D54 -> Canada | E11: 3.88 | F11: 25000 | G11: =E11*F11 -> 97000 | H11: 25000 | I11: =G11+H11 -> 122000 | J11: 22222 | K11: 33333 | L11: 11111 | M11: 12345 | N11: =IFERROR($I11/J11,"NA") -> 5.4900549 | O11: =IFERROR($I11/K11,"NA") -> 3.6600366 | P11: =IFERROR($G11/L11,"NA") -> 8.7300873 | Q11: =IFERROR($G11/M11,"NA") -> 7.8574322
B12: =Inputs!B55 -> Peer 2 | C12: =Inputs!C55 -> Industry 2 | D12: =Inputs!D55 -> USA | E12: 3.88 | F12: 25000 | G12: =E12*F12 -> 97000 | H12: 25000 | I12: =G12+H12 -> 122000 | J12: 22222 | K12: 33333 | L12: 11111 | M12: 12345 | N12: =IFERROR($I12/J12,"NA") -> 5.4900549 | O12: =IFERROR($I12/K12,"NA") -> 3.6600366 | P12: =IFERROR($G12/L12,"NA") -> 8.7300873 | Q12: =IFERROR($G12/M12,"NA") -> 7.8574322
B13: =Inputs!B56 -> Peer 3 | C13: =Inputs!C56 -> Industry 3 | D13: =Inputs!D56 -> USA | E13: 3.88 | F13: 25000 | G13: =E13*F13 -> 97000 | H13: 25000 | I13: =G13+H13 -> 122000 | J13: 22222 | K13: 33333 | L13: 11111 | M13: 12345 | N13: =IFERROR($I13/J13,"NA") -> 5.4900549 | O13: =IFERROR($I13/K13,"NA") -> 3.6600366 | P13: =IFERROR($G13/L13,"NA") -> 8.7300873 | Q13: =IFERROR($G13/M13,"NA") -> 7.8574322
B14: =Inputs!B57 -> Peer 4 | C14: =Inputs!C57 -> Industry 4 | D14: =Inputs!D57 -> USA | E14: 3.88 | F14: 25000 | G14: =E14*F14 -> 97000 | H14: 25000 | I14: =G14+H14 -> 122000 | J14: 22222 | K14: 33333 | L14: 11111 | M14: 12345 | N14: =IFERROR($I14/J14,"NA") -> 5.4900549 | O14: =IFERROR($I14/K14,"NA") -> 3.6600366 | P14: =IFERROR($G14/L14,"NA") -> 8.7300873 | Q14: =IFERROR($G14/M14,"NA") -> 7.8574322
B15: =Inputs!B58 -> Peer 5 | C15: =Inputs!C58 -> Industry 5 | D15: =Inputs!D58 -> Canada | E15: 3.88 | F15: 25000 | G15: =E15*F15 -> 97000 | H15: 25000 | I15: =G15+H15 -> 122000 | J15: 22222 | K15: 33333 | L15: 11111 | M15: 12345 | N15: =IFERROR($I15/J15,"NA") -> 5.4900549 | O15: =IFERROR($I15/K15,"NA") -> 3.6600366 | P15: =IFERROR($G15/L15,"NA") -> 8.7300873 | Q15: =IFERROR($G15/M15,"NA") -> 7.8574322
B16: =Inputs!B59 -> Peer 6 | C16: =Inputs!C59 -> Industry 6 | D16: =Inputs!D59 -> Canada | E16: 3.88 | F16: 25000 | G16: =E16*F16 -> 97000 | H16: 25000 | I16: =G16+H16 -> 122000 | J16: 22222 | K16: 33333 | L16: 11111 | M16: 12345 | N16: =IFERROR($I16/J16,"NA") -> 5.4900549 | O16: =IFERROR($I16/K16,"NA") -> 3.6600366 | P16: =IFERROR($G16/L16,"NA") -> 8.7300873 | Q16: =IFERROR($G16/M16,"NA") -> 7.8574322
B17: =Inputs!B60 -> Peer 7 | C17: =Inputs!C60 -> Industry 7 | D17: =Inputs!D60 -> USA | E17: 3.88 | F17: 25000 | G17: =E17*F17 -> 97000 | H17: 25000 | I17: =G17+H17 -> 122000 | J17: 22222 | K17: 33333 | L17: 11111 | M17: 12345 | N17: =IFERROR($I17/J17,"NA") -> 5.4900549 | O17: =IFERROR($I17/K17,"NA") -> 3.6600366 | P17: =IFERROR($G17/L17,"NA") -> 8.7300873 | Q17: =IFERROR($G17/M17,"NA") -> 7.8574322
B18: =Inputs!B61 -> Peer 8 | C18: =Inputs!C61 -> Industry 8 | D18: =Inputs!D61 -> Canada | E18: 3.88 | F18: 25000 | G18: =E18*F18 -> 97000 | H18: 25000 | I18: =G18+H18 -> 122000 | J18: 22222 | K18: 33333 | L18: 11111 | M18: 12345 | N18: =IFERROR($I18/J18,"NA") -> 5.4900549 | O18: =IFERROR($I18/K18,"NA") -> 3.6600366 | P18: =IFERROR($G18/L18,"NA") -> 8.7300873 | Q18: =IFERROR($G18/M18,"NA") -> 7.8574322
B19: =Inputs!B62 -> Peer 9 | C19: =Inputs!C62 -> Industry 9 | D19: =Inputs!D62 -> Ghana | E19: 3.88 | F19: 25000 | G19: =E19*F19 -> 97000 | H19: 25000 | I19: =G19+H19 -> 122000 | J19: 22222 | K19: 33333 | L19: 11111 | M19: 12345 | N19: =IFERROR($I19/J19,"NA") -> 5.4900549 | O19: =IFERROR($I19/K19,"NA") -> 3.6600366 | P19: =IFERROR($G19/L19,"NA") -> 8.7300873 | Q19: =IFERROR($G19/M19,"NA") -> 7.8574322
B20: =Inputs!B63 -> Peer 10 | C20: =Inputs!C63 -> Industry 10 | D20: =Inputs!D63 -> China | E20: 3.88 | F20: 25000 | G20: =E20*F20 -> 97000 | H20: 25000 | I20: =G20+H20 -> 122000 | J20: 22222 | K20: 33333 | L20: 11111 | M20: 12345 | N20: =IFERROR($I20/J20,"NA") -> 5.4900549 | O20: =IFERROR($I20/K20,"NA") -> 3.6600366 | P20: =IFERROR($G20/L20,"NA") -> 8.7300873 | Q20: =IFERROR($G20/M20,"NA") -> 7.8574322
B23: Average | N23: =+AVERAGE(N$11:N$16) -> 5.4900549 | O23: =+AVERAGE(O$11:O$16) -> 3.6600366 | P23: =+AVERAGE(P$11:P$16) -> 8.7300873 | Q23: =+AVERAGE(Q$11:Q$16) -> 7.8574322
B24: Median | N24: =+MEDIAN(N$11:N$16) -> 5.4900549 | O24: =+MEDIAN(O$11:O$16) -> 3.6600366 | P24: =+MEDIAN(P$11:P$16) -> 8.7300873 | Q24: =+MEDIAN(Q$11:Q$16) -> 7.8574322
B25: Maximum | N25: =+MAX(N$11:N$16) -> 5.4900549 | O25: =+MAX(O$11:O$16) -> 3.6600366 | P25: =+MAX(P$11:P$16) -> 8.7300873 | Q25: =+MAX(Q$11:Q$16) -> 7.8574322
B26: Minimum | N26: =+MIN(N$11:N$16) -> 5.4900549 | O26: =+MIN(O$11:O$16) -> 3.6600366 | P26: =+MIN(P$11:P$16) -> 8.7300873 | Q26: =+MIN(Q$11:Q$16) -> 7.8574322
B29: Target Company Value at Median Multiples
B30: =$J$9&"A EV/EBITDA" -> 2022A EV/EBITDA | E30: =G30/F30 -> 2.6352029 | F30: =Inputs!F113 -> 34200 | G30: =I30-H30 -> 90123.94 | H30: =Inputs!L102 -> 18642 | I30: =J30*N30 -> 108765.94 | J30: =Model!H562 -> 19811.448 | N30: =N24 -> 5.4900549
B31: =$K$9&"F EV/EBITDA" -> 2023F EV/EBITDA | E31: =G31/F31 -> 1.6205458 | F31: =F30 -> 34200 | G31: =I31-H31 -> 55422.665 | H31: =H30 -> 18642 | I31: =K31*O31 -> 74064.665 | K31: =Model!I562 -> 20236.045 | O31: =O24 -> 3.6600366
B32: =$L$9&"A P/E" -> 2022A P/E | E32: =G32/F32 -> 2.8565378 | F32: =F31 -> 34200 | G32: =L32*P32 -> 97693.592 | H32: =H31 -> 18642 | I32: =G32+H32 -> 116335.59 | L32: =Model!H554 -> 11190.448 | P32: =P24 -> 8.7300873
B33: =$M$9&"F P/E" -> 2023F P/E | E33: =G33/F33 -> 2.4549664 | F33: =F32 -> 34200 | G33: =+M33*Q33 -> 83959.849 | H33: =H32 -> 18642 | I33: =G33+H33 -> 102601.85 | M33: =Model!I554 -> 10685.406 | Q33: =Q24 -> 7.8574322
Q36: Enterprise Value = Market Cap + Net Debt.
Q37: Calculated as Market Cap divided by Net Income.
B42: Relative Valuation - Using Precedent Transaction Analysis
B44: All figures in USD thousands unless stated
E46: Share | F46: Offer | G46: Control | H46: Shares | I46: Market Cap | J46: Net | K46: Enterprise | L46: EBITDA | O46: EV / EBITDA
B47: Date | C47: Acquirer | D47: Target | E47: Price | F47: Price | G47: Premium | H47: Outstand. | I47: at Offer | J47: Debt | K47: Value | L47: 2022 | M47: 2023 | N47: 2024 | O47: 2022 | P47: 2023 | Q47: 2024
B48: (YYYY-MM-DD) | E48: $ | F48: $ | H48: mm | O48: x | P48: x | Q48: x
B49: 44631 | C49: Cake | D49: Ice Cream | E49: 25.5 | F49: 31.11 | G49: =F49/E49-1 -> 0.22 | H49: 129 | I49: =H49*F49 -> 4013.19 | J49: 2528.3097 | K49: =I49+J49 -> 6541.4997 | L49: 485 | M49: 509.25 | N49: 534.7125 | O49: =IFERROR($K49/L49,"NA") -> 13.487628 | P49: =IFERROR($K49/M49,"NA") -> 12.84536 | Q49: =IFERROR($K49/N49,"NA") -> 12.233676
B50: 44626 | C50: Salt | D50: Pepper | E50: 37.25 | F50: 46.56 | G50: =F50/E50-1 -> 0.24993289 | H50: 568 | I50: =H50*F50 -> 26446.08 | J50: 18247.795 | K50: =I50+J50 -> 44693.875 | L50: 4382 | M50: 4688.74 | N50: 5063.8392 | O50: =IFERROR($K50/L50,"NA") -> 10.199424 | P50: =IFERROR($K50/M50,"NA") -> 9.5321718 | Q50: =IFERROR($K50/N50,"NA") -> 8.826085
B51: 44456 | C51: Fish | D51: Chips | E51: 16.8 | F51: 21.17 | G51: =F51/E51-1 -> 0.26011905 | H51: 688 | I51: =H51*F51 -> 14564.96 | J51: 9758.5232 | K51: =I51+J51 -> 24323.483 | L51: 1622 | M51: 1784.2 | N51: 1891.252 | O51: =IFERROR($K51/L51,"NA") -> 14.995982 | P51: =IFERROR($K51/M51,"NA") -> 13.632711 | Q51: =IFERROR($K51/N51,"NA") -> 12.861048
B52: 44148 | C52: Peanut Butter | D52: Jelly | E52: 31.11 | F52: 37.33 | G52: =F52/E52-1 -> 0.19993571 | H52: 1429 | I52: =H52*F52 -> 53344.57 | J52: 34673.97 | K52: =I52+J52 -> 88018.541 | L52: 8075 | M52: 8882.5 | N52: 9681.925 | O52: =IFERROR($K52/L52,"NA") -> 10.900129 | P52: =IFERROR($K52/M52,"NA") -> 9.909208 | Q52: =IFERROR($K52/N52,"NA") -> 9.0910166
B53: 44056 | C53: Brisket | D53: NoSauce | E53: 29.29 | F53: 37.2 | G53: =F53/E53-1 -> 0.27005804 | H53: 1198 | I53: =H53*F53 -> 44565.6 | J53: 27630.672 | K53: =I53+J53 -> 72196.272 | L53: 4512 | M53: 4918.08 | N53: 5311.5264 | O53: =IFERROR($K53/L53,"NA") -> 16.000947 | P53: =IFERROR($K53/M53,"NA") -> 14.679768 | Q53: =IFERROR($K53/N53,"NA") -> 13.592378
B54: 43952 | C54: Biscuits | D54: Gravy | E54: 12.34 | F54: 15.3 | G54: =F54/E54-1 -> 0.23987034 | H54: 934 | I54: =H54*F54 -> 14290.2 | J54: 9145.728 | K54: =I54+J54 -> 23435.928 | L54: 2092 | M54: 2280.28 | N54: 2485.5052 | O54: =IFERROR($K54/L54,"NA") -> 11.202642 | P54: =IFERROR($K54/M54,"NA") -> 10.277654 | Q54: =IFERROR($K54/N54,"NA") -> 9.42904
B55: 44091 | C55: CTM | D55: GTM | E55: 9 | F55: 8.75 | G55: =F55/E55-1 -> -0.027777778 | H55: 156 | I55: =H55*F55 -> 1365 | J55: 859.95 | K55: =I55+J55 -> 2224.95 | L55: 371 | M55: 404.39 | N55: 424.6095 | O55: =IFERROR($K55/L55,"NA") -> 5.9971698 | P55: =IFERROR($K55/M55,"NA") -> 5.5019907 | Q55: =IFERROR($K55/N55,"NA") -> 5.2399911
B56: 42264 | C56: CTM | D56: Jik | E56: 23.82 | F56: 30.4896 | G56: =F56/E56-1 -> 0.28 | H56: 1219 | I56: =H56*F56 -> 37166.822 | J56: 25273.439 | K56: =I56+J56 -> 62440.262 | L56: 4995 | M56: 5144.85 | N56: 5299.1955 | O56: =IFERROR($K56/L56,"NA") -> 12.500553 | P56: =IFERROR($K56/M56,"NA") -> 12.136459 | Q56: =IFERROR($K56/N56,"NA") -> 11.78297
B57: 41956 | C57: Octane | D57: Lime | E57: 60 | F57: 72.5 | G57: =F57/E57-1 -> 0.20833333 | H57: 141 | I57: =H57*F57 -> 10222.5 | J57: 6337.95 | K57: =I57+J57 -> 16560.45 | L57: 974 | M57: 1071.4 | N57: 1178.54 | O57: =IFERROR($K57/L57,"NA") -> 17.002515 | P57: =IFERROR($K57/M57,"NA") -> 15.456832 | Q57: =IFERROR($K57/N57,"NA") -> 14.051666
B58: 41864 | C58: HHV | D58: Dela | E58: 14 | F58: 17.36 | G58: =F58/E58-1 -> 0.24 | H58: 1377 | I58: =H58*F58 -> 23904.72 | J58: 14342.832 | K58: =I58+J58 -> 38247.552 | L58: 2318 | M58: 2503.44 | N58: 2728.7496 | O58: =IFERROR($K58/L58,"NA") -> 16.500238 | P58: =IFERROR($K58/M58,"NA") -> 15.277998 | Q58: =IFERROR($K58/N58,"NA") -> 14.016512
B61: Average | O61: =+AVERAGE(O$49:O$54) -> 12.797792 | P61: =+AVERAGE(P$49:P$54) -> 11.812812 | Q61: =+AVERAGE(Q$49:Q$54) -> 11.005541
B62: Median | O62: =+MEDIAN(O$49:O$54) -> 12.345135 | P62: =+MEDIAN(P$49:P$54) -> 11.561507 | Q62: =+MEDIAN(Q$49:Q$54) -> 10.831358
B63: Maximum | O63: =+MAX(O$49:O$54) -> 16.000947 | P63: =+MAX(P$49:P$54) -> 14.679768 | Q63: =+MAX(Q$49:Q$54) -> 13.592378
B64: Minimum | O64: =+MIN(O$49:O$54) -> 10.199424 | P64: =+MIN(P$49:P$54) -> 9.5321718 | Q64: =+MIN(Q$49:Q$54) -> 8.826085
B67: Target Company Value at Median Multiples
B68: =$L$47&"A EV/EBITDA" -> 2022A EV/EBITDA | E68: =Inputs!F116 -> 7 | F68: =I68/H68 -> 6.6062285 | G68: =F68/E68-1 -> -0.056253078 | H68: =Inputs!F113 -> 34200 | I68: =K68-J68 -> 225933.01 | J68: =Inputs!L102 -> 18642 | K68: =L68*O68 -> 244575.01 | L68: =Model!H562 -> 19811.448 | O68: =O62 -> 12.345135
B69: =$M$47&"F EV/EBITDA" -> 2023F EV/EBITDA | E69: =E68 -> 7 | F69: =I69/H69 -> 6.2958238 | G69: =F69/E69-1 -> -0.1005966 | H69: =H68 -> 34200 | I69: =K69-J69 -> 215317.17 | J69: =J68 -> 18642 | K69: =M69*P69 -> 233959.17 | M69: =Model!I562 -> 20236.045 | P69: =P62 -> 11.561507
B70: =$N$47&"F EV/EBITDA" -> 2024F EV/EBITDA | E70: =E69 -> 7 | F70: =I70/H70 -> 5.8806914 | G70: =F70/E70-1 -> -0.15990123 | H70: =H69 -> 34200 | I70: =K70-J70 -> 201119.65 | J70: =J69 -> 18642 | K70: =N70*Q70 -> 219761.65 | N70: =Model!J562 -> 20289.39 | Q70: =Q62 -> 10.831358

Sheet Football Field Chart
B3: Football Field Chart
E36: Low | F36: Middle | G36: High
D37: Comparable Companies | E37: =MIN('Relative Valuation'!E30:E33) -> 1.6205458 | F37: =G37-E37 -> 1.235992 | G37: =MAX('Relative Valuation'!E30:E33) -> 2.8565378
D38: Precedent Transactions | E38: =MIN('Relative Valuation'!F68:F70) -> 5.8806914 | F38: =G38-E38 -> 0.72553705 | G38: =MAX('Relative Valuation'!F68:F70) -> 6.6062285
D39: DCF - Perpetuity Growth | E39: =Model!D739 -> 2.8323072 | F39: =G39-E39 -> 1.6855227 | G39: =Model!H743 -> 4.5178299
D40: DCF - Terminal Multiple | E40: =Model!D750 -> 2.5816457 | F40: =G40-E40 -> 1.9964775 | G40: =Model!H754 -> 4.5781231
D41: 52 Week High/Low | E41: =Inputs!L107 -> 3.2 | F41: =G41-E41 -> 1.8 | G41: =Inputs!L106 -> 5
D42: ="Average Valuation: "&TEXT(E42,"$0.00") -> Average Valuation: $3.93 | E42: =AVERAGE(E37:E40,G37:G40) -> 3.9342386

Sheet Model-R
B3: Revenue Schedule
B5: All figures in USD thousands unless stated | F5: =G5-1 -> 2020 | G5: =H5-1 -> 2021 | H5: =I5-1 -> 2022 | I5: =Inputs!F105 -> 2023 | J5: =I5+1 -> 2024 | K5: =J5+1 -> 2025 | L5: =K5+1 -> 2026 | M5: =L5+1 -> 2027 | N5: Term
B6: {=CONCATENATE("Model Running: ",INDEX(Inputs!$B$12:$B$14,Inputs!$D$7)," Drivers")} -> Model Running: Base Case Drivers
B8: Days in Period | C8: =Inputs!F108 -> 365 | F8: 365 | G8: 365 | H8: 365 | I8: =$C$8 -> 365 | J8: =$C$8 -> 365 | K8: =$C$8 -> 365 | L8: =$C$8 -> 365 | M8: =$C$8 -> 365 | N8: =$C$8 -> 365
B9: Plant Capacity | C9: =Inputs!#REF! -> #REF!
B12: OPERATIONS
Q13: Learner | R13: Correct | S13: Compare
B14: Sales Volume Growth | G14: =G16/F16-1 -> 0.019650655 | H14: =H16/G16-1 -> 0.0206995 | I14: =Inputs!G10 -> 0.03 | J14: =Inputs!H10 -> 0.02 | K14: =Inputs!I10 -> 0.02 | L14: =Inputs!J10 -> 0.015 | M14: =Inputs!K10 -> 0.015 | N14: =Inputs!L10 -> 0.01 | Q14: =SUM(Model!#REF!) -> #REF! | R14: =SUM(Inputs!G10:L10) -> 0.11 | S14: =IF(ISBLANK(Model!#REF!),0,IF(Q14=R14,1,0)) -> #REF!
B16: Sales Volume | D16: (Units/Day) | F16: 1374 | G16: 1401 | H16: 1430 | I16: =H16*(1+I14) -> 1472.9 | J16: =I16*(1+J14) -> 1502.358 | K16: =J16*(1+K14) -> 1532.4052 | L16: =K16*(1+L14) -> 1555.3912 | M16: =L16*(1+M14) -> 1578.7221 | N16: =M16*(1+N14) -> 1594.5093
B17: Plant Capacity | D17: (Units/Day) | F17: 1600 | G17: 1600 | H17: 1600 | I17: =$C$9 -> #REF! | J17: =$C$9 -> #REF! | K17: =$C$9 -> #REF! | L17: =$C$9 -> #REF! | M17: =$C$9 -> #REF! | N17: =$C$9 -> #REF!
B18: Operational Efficiency | F18: =F16/F17 -> 0.85875 | G18: =G16/G17 -> 0.875625 | H18: =H16/H17 -> 0.89375 | I18: =I16/I17 -> #REF! | J18: =J16/J17 -> #REF! | K18: =K16/K17 -> #REF! | L18: =L16/L17 -> #REF! | M18: =M16/M17 -> #REF! | N18: =N16/N17 -> #REF!
B23: VOLUME
B25: Days in Period | F25: =F8 -> 365 | G25: =G8 -> 365 | H25: =H8 -> 365 | I25: =I8 -> 365 | J25: =J8 -> 365 | K25: =K8 -> 365 | L25: =L8 -> 365 | M25: =M8 -> 365 | N25: =N8 -> 365
B26: Sales Volume | D26: (Units/Day) | F26: =F16 -> 1374 | G26: =G16 -> 1401 | H26: =H16 -> 1430 | I26: =I16 -> 1472.9 | J26: =J16 -> 1502.358 | K26: =K16 -> 1532.4052 | L26: =L16 -> 1555.3912 | M26: =M16 -> 1578.7221 | N26: =N16 -> 1594.5093
B27: Sales Volume | D27: (Units) | F27: =F26*F25 -> 501510 | G27: =G26*G25 -> 511365 | H27: =H26*H25 -> 521950 | I27: =I26*I25 -> 537608.5 | J27: =J26*J25 -> 548360.67 | K27: =K26*K25 -> 559327.88 | L27: =L26*L25 -> 567717.8 | M27: =M26*M25 -> 576233.57 | N27: =N26*N25 -> 581995.9
B30: PRICING
Q31: Learner | R31: Correct | S31: Compare
B32: Pricing Increases | G32: =G33/F33-1 -> 0.017013416 | H32: =H33/G33-1 -> 0.021030494 | I32: =Inputs!G17 -> 0.035 | J32: =Inputs!H17 -> 0.03 | K32: =Inputs!I17 -> 0.03 | L32: =Inputs!J17 -> 0.025 | M32: =Inputs!K17 -> 0.025 | N32: =Inputs!L17 -> 0.015 | Q32: =SUM(Model!#REF!) -> #REF! | R32: =SUM(Inputs!G17:L17) -> 0.16 | S32: =IF(ISBLANK(Model!#REF!),0,IF(Q32=R32,1,0)) -> #REF!
B33: Unit Price | D33: (USD/Unit) | F33: 102.86 | G33: 104.61 | H33: 106.81 | I33: =H33*(1+I32) -> 110.54835 | J33: =I33*(1+J32) -> 113.8648 | K33: =J33*(1+K32) -> 117.28074 | L33: =K33*(1+L32) -> 120.21276 | M33: =L33*(1+M32) -> 123.21808 | N33: =M33*(1+N32) -> 125.06635
B36: REVENUE
B38: Sales Volume | D38: (Units) | F38: =F27 -> 501510 | G38: =G27 -> 511365 | H38: =H27 -> 521950 | I38: =I27 -> 537608.5 | J38: =J27 -> 548360.67 | K38: =K27 -> 559327.88 | L38: =L27 -> 567717.8 | M38: =M27 -> 576233.57 | N38: =N27 -> 581995.9
B39: Sales Price | D39: (USD/Unit) | F39: =F33 -> 102.86 | G39: =G33 -> 104.61 | H39: =H33 -> 106.81 | I39: =I33 -> 110.54835 | J39: =J33 -> 113.8648 | K39: =K33 -> 117.28074 | L39: =L33 -> 120.21276 | M39: =M33 -> 123.21808 | N39: =N33 -> 125.06635
B40: Revenue | F40: =F38*F39/1000 -> 51585.319 | G40: =G38*G39/1000 -> 53493.893 | H40: =H38*H39/1000 -> 55749.48 | I40: =I38*I39/1000 -> 59431.733 | J40: =J38*J39/1000 -> 62438.978 | K40: =K38*K39/1000 -> 65598.391 | L40: =L38*L39/1000 -> 68246.926 | M40: =M38*M39/1000 -> 71002.395 | N40: =N38*N39/1000 -> 72788.105
B43: Operational Capacity Exceeded? | F43: =IF(F18>=1,1,0) -> 0 | G43: =IF(G18>=1,1,0) -> 0 | H43: =IF(H18>=1,1,0) -> 0 | I43: =IF(I18>=1,1,0) -> #REF! | J43: =IF(J18>=1,1,0) -> #REF! | K43: =IF(K18>=1,1,0) -> #REF! | L43: =IF(L18>=1,1,0) -> #REF! | M43: =IF(M18>=1,1,0) -> #REF! | N43: =IF(N18>=1,1,0) -> #REF! | S43: =IF(SUM(S13:S40)=2,"COMPLETE","") -> #REF!
B47: Cost Schedule
B49: All figures in USD thousands unless stated | F49: =F$5 -> 2020 | G49: =G$5 -> 2021 | H49: =H$5 -> 2022 | I49: =I$5 -> 2023 | J49: =J$5 -> 2024 | K49: =K$5 -> 2025 | L49: =L$5 -> 2026 | M49: =M$5 -> 2027 | N49: =N$5 -> Term
B50: =$B$6 -> Model Running: Base Case Drivers
B52: Sales Volume | F52: =F38 -> 501510 | G52: =G38 -> 511365 | H52: =H38 -> 521950 | I52: =I38 -> 537608.5 | J52: =J38 -> 548360.67 | K52: =K38 -> 559327.88 | L52: =L38 -> 567717.8 | M52: =M38 -> 576233.57 | N52: =N38 -> 581995.9 | Q52: Learner | R52: Correct | S52: Compare
B53: Inflation | F53: 0.024 | G53: 0.022 | H53: 0.023 | I53: =Inputs!G31 -> 0.035 | J53: =Inputs!H31 -> 0.03 | K53: =Inputs!I31 -> 0.03 | L53: =Inputs!J31 -> 0.025 | M53: =Inputs!K31 -> 0.025 | N53: =Inputs!L31 -> 0.015 | Q53: =SUM(Model!I7:N7) -> 0.16 | R53: =SUM(I53:N53) -> 0.16 | S53: =IF(ISBLANK(Model!I7),0,IF(Q53=R53,1,0)) -> 1
B55: VARIABLE COSTS
B57: Materials | D57: (USD/Unit) | F57: 9.51 | G57: 9.72 | H57: 9.91 | I57: =H57*(1+I$53) -> 10.25685 | J57: =I57*(1+J$53) -> 10.564556 | K57: =J57*(1+K$53) -> 10.881492 | L57: =K57*(1+L$53) -> 11.153529 | M57: =L57*(1+M$53) -> 11.432368 | N57: =M57*(1+N$53) -> 11.603853
B58: Packaging | D58: (USD/Unit) | F58: 0.82 | G58: 0.84 | H58: 0.86 | I58: =H58*(1+I$53) -> 0.8901 | J58: =I58*(1+J$53) -> 0.916803 | K58: =J58*(1+K$53) -> 0.94430709 | L58: =K58*(1+L$53) -> 0.96791477 | M58: =L58*(1+M$53) -> 0.99211264 | N58: =M58*(1+N$53) -> 1.0069943
B59: Transportation | D59: (USD/Unit) | F59: 1.54 | G59: 1.58 | H59: 1.62 | I59: =H59*(1+I$53) -> 1.6767 | J59: =I59*(1+J$53) -> 1.727001 | K59: =J59*(1+K$53) -> 1.778811 | L59: =K59*(1+L$53) -> 1.8232813 | M59: =L59*(1+M$53) -> 1.8688633 | N59: =M59*(1+N$53) -> 1.8968963
B60: Subtotal | F60: =SUM(F57:F59) -> 11.87 | G60: =SUM(G57:G59) -> 12.14 | H60: =SUM(H57:H59) -> 12.39 | I60: =SUM(I57:I59) -> 12.82365 | J60: =SUM(J57:J59) -> 13.20836 | K60: =SUM(K57:K59) -> 13.60461 | L60: =SUM(L57:L59) -> 13.944726 | M60: =SUM(M57:M59) -> 14.293344 | N60: =SUM(N57:N59) -> 14.507744
B62: Materials | F62: =F57*F$52/1000 -> 4769.3601 | G62: =G57*G$52/1000 -> 4970.4678 | H62: =H57*H$52/1000 -> 5172.5245 | I62: =I57*I$52/1000 -> 5514.1697 | J62: =J57*J$52/1000 -> 5793.1867 | K62: =K57*K$52/1000 -> 6086.322 | L62: =L57*L$52/1000 -> 6332.0572 | M62: =M57*M$52/1000 -> 6587.714 | N62: =N57*N$52/1000 -> 6753.395
B63: Packaging | F63: =F58*F$52/1000 -> 411.2382 | G63: =G58*G$52/1000 -> 429.5466 | H63: =H58*H$52/1000 -> 448.877 | I63: =I58*I$52/1000 -> 478.52533 | J63: =J58*J$52/1000 -> 502.73871 | K63: =K58*K$52/1000 -> 528.17729 | L63: =L58*L$52/1000 -> 549.50244 | M63: =M58*M$52/1000 -> 571.68861 | N63: =N58*N$52/1000 -> 586.06657
B64: Transportation | F64: =F59*F$52/1000 -> 772.3254 | G64: =G59*G$52/1000 -> 807.9567 | H64: =H59*H$52/1000 -> 845.559 | I64: =I59*I$52/1000 -> 901.40817 | J64: =J59*J$52/1000 -> 947.01943 | K64: =K59*K$52/1000 -> 994.93861 | L64: =L59*L$52/1000 -> 1035.1093 | M64: =M59*M$52/1000 -> 1076.9018 | N64: =N59*N$52/1000 -> 1103.9859
B65: Subtotal | F65: =SUM(F62:F64) -> 5952.9237 | G65: =SUM(G62:G64) -> 6207.9711 | H65: =SUM(H62:H64) -> 6466.9605 | I65: =SUM(I62:I64) -> 6894.1032 | J65: =SUM(J62:J64) -> 7242.9449 | K65: =SUM(K62:K64) -> 7609.4379 | L65: =SUM(L62:L64) -> 7916.6689 | M65: =SUM(M62:M64) -> 8236.3044 | N65: =SUM(N62:N64) -> 8443.4475
B68: FIXED COSTS
B70: Labor | D70: (USD/Unit) | F70: =(F75*1000)/F$52 -> 31.165879 | G70: =(G75*1000)/G$52 -> 31.236006 | H70: =(H75*1000)/H$52 -> 31.307597 | I70: =(I75*1000)/I$52 -> 31.459575 | J70: =(J75*1000)/J$52 -> 31.768002 | K70: =(K75*1000)/K$52 -> 32.079453 | L70: =(L75*1000)/L$52 -> 32.395507 | M70: =(M75*1000)/M$52 -> 32.714675 | N70: =(N75*1000)/N$52 -> 32.876628
B71: Utilities | D71: (USD/Unit) | F71: =(F76*1000)/F$52 -> 7.2800144 | G71: =(G76*1000)/G$52 -> 7.2961583 | H71: =(H76*1000)/H$52 -> 7.312961 | I71: =(I76*1000)/I$52 -> 7.3484608 | J71: =(J76*1000)/J$52 -> 7.4205046 | K71: =(K76*1000)/K$52 -> 7.4932546 | L71: =(L76*1000)/L$52 -> 7.5670798 | M71: =(M76*1000)/M$52 -> 7.6416323 | N71: =(N76*1000)/N$52 -> 7.6794621
B72: Insurance | D72: (USD/Unit) | F72: =(F77*1000)/F$52 -> 4.9111683 | G72: =(G77*1000)/G$52 -> 4.9221202 | H72: =(H77*1000)/H$52 -> 4.9334227 | I72: =(I77*1000)/I$52 -> 4.9573714 | J72: =(J77*1000)/J$52 -> 5.0059731 | K72: =(K77*1000)/K$52 -> 5.0550512 | L72: =(L77*1000)/L$52 -> 5.1048547 | M72: =(M77*1000)/M$52 -> 5.1551488 | N72: =(N77*1000)/N$52 -> 5.1806694
B73: Subtotal | F73: =SUM(F70:F72) -> 43.357062 | G73: =SUM(G70:G72) -> 43.454284 | H73: =SUM(H70:H72) -> 43.55398 | I73: =SUM(I70:I72) -> 43.765407 | J73: =SUM(J70:J72) -> 44.19448 | K73: =SUM(K70:K72) -> 44.627759 | L73: =SUM(L70:L72) -> 45.067442 | M73: =SUM(M70:M72) -> 45.511456 | N73: =SUM(N70:N72) -> 45.73676
B75: Labor | F75: 15630 | G75: 15973 | H75: 16341 | I75: =H75*(1+I$53) -> 16912.935 | J75: =I75*(1+J$53) -> 17420.323 | K75: =J75*(1+K$53) -> 17942.933 | L75: =K75*(1+L$53) -> 18391.506 | M75: =L75*(1+M$53) -> 18851.294 | N75: =M75*(1+N$53) -> 19134.063
B76: Utilities | F76: 3651 | G76: 3731 | H76: 3817 | I76: =H76*(1+I$53) -> 3950.595 | J76: =I76*(1+J$53) -> 4069.1128 | K76: =J76*(1+K$53) -> 4191.1862 | L76: =K76*(1+L$53) -> 4295.9659 | M76: =L76*(1+M$53) -> 4403.365 | N76: =M76*(1+N$53) -> 4469.4155
B77: Insurance | F77: 2463 | G77: 2517 | H77: 2575 | I77: =H77*(1+I$53) -> 2665.125 | J77: =I77*(1+J$53) -> 2745.0788 | K77: =J77*(1+K$53) -> 2827.4311 | L77: =K77*(1+L$53) -> 2898.1169 | M77: =L77*(1+M$53) -> 2970.5698 | N77: =M77*(1+N$53) -> 3015.1284
B78: Subtotal | F78: =SUM(F75:F77) -> 21744 | G78: =SUM(G75:G77) -> 22221 | H78: =SUM(H75:H77) -> 22733 | I78: =SUM(I75:I77) -> 23528.655 | J78: =SUM(J75:J77) -> 24234.515 | K78: =SUM(K75:K77) -> 24961.55 | L78: =SUM(L75:L77) -> 25585.589 | M78: =SUM(M75:M77) -> 26225.229 | N78: =SUM(N75:N77) -> 26618.607
B81: SUMMARY
B83: Variable Costs | D83: (USD/Unit) | F83: =F60 -> 11.87 | G83: =G60 -> 12.14 | H83: =H60 -> 12.39 | I83: =I60 -> 12.82365 | J83: =J60 -> 13.20836 | K83: =K60 -> 13.60461 | L83: =L60 -> 13.944726 | M83: =M60 -> 14.293344 | N83: =N60 -> 14.507744
B84: Fixed Costs | D84: (USD/Unit) | F84: =F73 -> 43.357062 | G84: =G73 -> 43.454284 | H84: =H73 -> 43.55398 | I84: =I73 -> 43.765407 | J84: =J73 -> 44.19448 | K84: =K73 -> 44.627759 | L84: =L73 -> 45.067442 | M84: =M73 -> 45.511456 | N84: =N73 -> 45.73676
B85: Total Costs | D85: (USD/Unit) | F85: =SUM(F83:F84) -> 55.227062 | G85: =SUM(G83:G84) -> 55.594284 | H85: =SUM(H83:H84) -> 55.94398 | I85: =SUM(I83:I84) -> 56.589057 | J85: =SUM(J83:J84) -> 57.402839 | K85: =SUM(K83:K84) -> 58.232369 | L85: =SUM(L83:L84) -> 59.012167 | M85: =SUM(M83:M84) -> 59.804799 | N85: =SUM(N83:N84) -> 60.244504
B87: Variable Costs | F87: =F65 -> 5952.9237 | G87: =G65 -> 6207.9711 | H87: =H65 -> 6466.9605 | I87: =I65 -> 6894.1032 | J87: =J65 -> 7242.9449 | K87: =K65 -> 7609.4379 | L87: =L65 -> 7916.6689 | M87: =M65 -> 8236.3044 | N87: =N65 -> 8443.4475
B88: Fixed Costs | F88: =F78 -> 21744 | G88: =G78 -> 22221 | H88: =H78 -> 22733 | I88: =I78 -> 23528.655 | J88: =J78 -> 24234.515 | K88: =K78 -> 24961.55 | L88: =L78 -> 25585.589 | M88: =M78 -> 26225.229 | N88: =N78 -> 26618.607
B89: Total Costs | F89: =SUM(F87:F88) -> 27696.924 | G89: =SUM(G87:G88) -> 28428.971 | H89: =SUM(H87:H88) -> 29199.961 | I89: =SUM(I87:I88) -> 30422.758 | J89: =SUM(J87:J88) -> 31477.46 | K89: =SUM(K87:K88) -> 32570.988 | L89: =SUM(L87:L88) -> 33502.258 | M89: =SUM(M87:M88) -> 34461.533 | N89: =SUM(N87:N88) -> 35062.054 | S89: =IF(SUM(S52:S86)=1,"COMPLETE","") -> COMPLETE
B93: Income Statement
B95: All figures in USD thousands unless stated | F95: =F$5 -> 2020 | G95: =G$5 -> 2021 | H95: =H$5 -> 2022 | I95: =I$5 -> 2023 | J95: =J$5 -> 2024 | K95: =K$5 -> 2025 | L95: =L$5 -> 2026 | M95: =M$5 -> 2027 | N95: =N$5 -> Term
B96: =$B$6 -> Model Running: Base Case Drivers
B98: Inflation | F98: =F53 -> 0.024 | G98: =G53 -> 0.022 | H98: =H53 -> 0.023 | I98: =I53 -> 0.035 | J98: =J53 -> 0.03 | K98: =K53 -> 0.03 | L98: =L53 -> 0.025 | M98: =M53 -> 0.025 | N98: =N53 -> 0.015
B100: Interest Expense | C100: =Inputs!#REF! -> #REF!
B101: Tax Rate | C101: =Inputs!L81 -> 0.25
Q102: Learner | R102: Correct | S102: Compare
B103: Revenue | F103: 51585 | G103: 53494 | H103: 55749 | I103: =Model!#REF! -> #REF! | J103: =Model!#REF! -> #REF! | K103: =Model!#REF! -> #REF! | L103: =Model!#REF! -> #REF! | M103: =Model!#REF! -> #REF! | N103: =Model!#REF! -> #REF! | Q103: =SUM(Model!I19:N19) -> 347238.17 | R103: =SUM(I103:N103) -> #REF! | S103: =IF(ISBLANK(Model!I19),0,IF(Q103=R103,1,0)) -> #REF!
B104: COGS | F104: 27697 | G104: 28429 | H104: 29200 | I104: =Model!#REF! -> #REF! | J104: =Model!#REF! -> #REF! | K104: =Model!#REF! -> #REF! | L104: =Model!#REF! -> #REF! | M104: =Model!#REF! -> #REF! | N104: =Model!#REF! -> #REF! | Q104: =SUM(Model!I20:N20) -> -171409.99 | R104: =SUM(I104:N104) -> #REF! | S104: =IF(ISBLANK(Model!I20),0,IF(Q104=R104,1,0)) -> #REF!
B105: Gross Profit | F105: =F103-F104 -> 23888 | G105: =G103-G104 -> 25065 | H105: =H103-H104 -> 26549 | I105: =I103-I104 -> #REF! | J105: =J103-J104 -> #REF! | K105: =K103-K104 -> #REF! | L105: =L103-L104 -> #REF! | M105: =M103-M104 -> #REF! | N105: =N103-N104 -> #REF!
Q107: Learner | R107: Correct | S107: Compare
B108: SG&A | F108: 5877 | G108: 6006 | H108: 6144 | I108: =H108*(1+Model!I$14) -> 6359.04 | J108: =I108*(1+Model!J$14) -> 6549.8112 | K108: =J108*(1+Model!K$14) -> 6746.3055 | L108: =K108*(1+Model!L$14) -> 6914.9632 | M108: =L108*(1+Model!M$14) -> 7087.8373 | N108: =M108*(1+Model!N$14) -> 7194.1548 | Q108: =SUM(Model!I24:N24) -> -40852.112 | R108: =SUM(I108:N108) -> 40852.112 | S108: =IF(ISBLANK(Model!I24),0,IF(Q108=R108,1,0)) -> 0
B109: Other | F109: 1764 | G109: 1931 | H109: 2026 | I109: =H109*(1+Model!I$14) -> 2096.91 | J109: =I109*(1+Model!J$14) -> 2159.8173 | K109: =J109*(1+Model!K$14) -> 2224.6118 | L109: =K109*(1+Model!L$14) -> 2280.2271 | M109: =L109*(1+Model!M$14) -> 2337.2328 | N109: =M109*(1+Model!N$14) -> 2372.2913 | Q109: =SUM(Model!I25:N25) -> -13471.09 | R109: =SUM(I109:N109) -> 13471.09 | S109: =IF(ISBLANK(Model!I25),0,IF(Q109=R109,1,0)) -> 0
B110: EBITDA | F110: =F105-SUM(F108:F109) -> 16247 | G110: =G105-SUM(G108:G109) -> 17128 | H110: =H105-SUM(H108:H109) -> 18379 | I110: =I105-SUM(I108:I109) -> #REF! | J110: =J105-SUM(J108:J109) -> #REF! | K110: =K105-SUM(K108:K109) -> #REF! | L110: =L105-SUM(L108:L109) -> #REF! | M110: =M105-SUM(M108:M109) -> #REF! | N110: =N105-SUM(N108:N109) -> #REF!
Q112: Learner | R112: Correct | S112: Compare
B113: Depreciation | F113: 2960 | G113: 3196 | H113: 3452 | I113: =Model!I197 -> 4962.9375 | J113: =Model!J197 -> 5412.9375 | K113: =Model!K197 -> 5837.9375 | L113: =Model!L197 -> 6187.9375 | M113: =Model!M197 -> 6437.9375 | N113: =Inputs!L24 -> 6000 | Q113: =SUM(Model!I29:N29) -> -35552.625 | R113: =SUM(Model!I197:M197)+Inputs!L24 -> 34839.688 | S113: =IF(ISBLANK(Model!I29),0,IF(Q113=R113,1,0)) -> 0
B114: EBIT | F114: =F110-F113 -> 13287 | G114: =G110-G113 -> 13932 | H114: =H110-H113 -> 14927 | I114: =I110-I113 -> #REF! | J114: =J110-J113 -> #REF! | K114: =K110-K113 -> #REF! | L114: =L110-L113 -> #REF! | M114: =M110-M113 -> #REF! | N114: =N110-N113 -> #REF!
Q115: Learner | R115: Correct | S115: Compare
B116: Interest | F116: 1488 | G116: 2580 | H116: 2448 | I116: =$C$100 -> #REF! | J116: =$C$100 -> #REF! | K116: =$C$100 -> #REF! | L116: =$C$100 -> #REF! | M116: =$C$100 -> #REF! | N116: =$C$100 -> #REF! | Q116: =SUM(Model!I33:N33) -> 1077.1241 | R116: =SUM(I116:N116) -> #REF! | S116: =IF(ISBLANK(Model!I33),0,IF(Q116=R116,1,0)) -> #REF!
B117: EBT | F117: =F114-F116 -> 11799 | G117: =G114-G116 -> 11352 | H117: =H114-H116 -> 12479 | I117: =I114-I116 -> #REF! | J117: =J114-J116 -> #REF! | K117: =K114-K116 -> #REF! | L117: =L114-L116 -> #REF! | M117: =M114-M116 -> #REF! | N117: =N114-N116 -> #REF!
Q118: Learner | R118: Correct | S118: Compare
B119: Current Tax | F119: 0 | G119: 0 | H119: 0 | I119: =Model!I363 -> 0 | J119: =Model!J363 -> 233.41219 | K119: =Model!K363 -> 3125.0759 | L119: =Model!L363 -> 3159.6576 | M119: =Model!M363 -> 3280.7926 | N119: =C101*Model!N34 -> 3369.1696 | Q119: =SUM(Model!I36:N36) -> 13168.108 | R119: =SUM(I119:N119) -> 13168.108 | S119: =IF(ISBLANK(Model!I36),0,IF(Q119=R119,1,0)) -> 1
B120: Deferred Tax | F120: 3155 | G120: 2861 | H120: 3012 | I120: =Model!I364 -> 3561.8019 | J120: =Model!J364 -> 3280.8675 | K120: =Model!K364 -> 343.98241 | L120: =Model!L364 -> 248.46239 | M120: =Model!M364 -> 104.14537 | N120: 0 | Q120: =SUM(Model!I37:N37) -> 7539.2595 | R120: =SUM(I120:N120) -> 7539.2595 | S120: =IF(ISBLANK(Model!I37),0,IF(Q120=R120,1,0)) -> 1
B121: Total Tax | F121: =SUM(F119:F120) -> 3155 | G121: =SUM(G119:G120) -> 2861 | H121: =SUM(H119:H120) -> 3012 | I121: =SUM(I119:I120) -> 3561.8019 | J121: =SUM(J119:J120) -> 3514.2797 | K121: =SUM(K119:K120) -> 3469.0583 | L121: =SUM(L119:L120) -> 3408.12 | M121: =SUM(M119:M120) -> 3384.938 | N121: =SUM(N119:N120) -> 3369.1696
B123: Net Income | F123: =F117-F121 -> 8644 | G123: =G117-G121 -> 8491 | H123: =H117-H121 -> 9467 | I123: =I117-I121 -> #REF! | J123: =J117-J121 -> #REF! | K123: =K117-K121 -> #REF! | L123: =L117-L121 -> #REF! | M123: =M117-M121 -> #REF! | N123: =N117-N121 -> #REF! | S123: =IF(SUM(S102:S120)=8,"COMPLETE","") -> #REF!
B127: Working Capital Schedule
B129: All figures in USD thousands unless stated | F129: =F$5 -> 2020 | G129: =G$5 -> 2021 | H129: =H$5 -> 2022 | I129: =I$5 -> 2023 | J129: =J$5 -> 2024 | K129: =K$5 -> 2025 | L129: =L$5 -> 2026 | M129: =M$5 -> 2027 | N129: Term
B130: =$B$6 -> Model Running: Base Case Drivers
B132: Days in Period | F132: =F$8 -> 365 | G132: =G$8 -> 365 | H132: =H$8 -> 365 | I132: =I$8 -> 365 | J132: =J$8 -> 365 | K132: =K$8 -> 365 | L132: =L$8 -> 365 | M132: =M$8 -> 365 | N132: =N$8 -> 365
B133: Revenue | F133: =F103 -> 51585 | G133: =G103 -> 53494 | H133: =H103 -> 55749 | I133: =I103 -> #REF! | J133: =J103 -> #REF! | K133: =K103 -> #REF! | L133: =L103 -> #REF! | M133: =M103 -> #REF! | N133: =N103 -> #REF!
B134: COGS | F134: =F104 -> 27697 | G134: =G104 -> 28429 | H134: =H104 -> 29200 | I134: =I104 -> #REF! | J134: =J104 -> #REF! | K134: =K104 -> #REF! | L134: =L104 -> #REF! | M134: =M104 -> #REF! | N134: =N104 -> #REF!
B137: AMOUNTS PER DAY 1 | Q137: Learner | R137: Correct | S137: Compare
B138: Accounts Receivable | D138: (Days) | F138: =(F144/F133)*F$132 -> 40.388097 | G138: =(G144/G133)*G$132 -> 43.211295 | H138: =(H144/H133)*H$132 -> 43.36867 | I138: =Inputs!G35 -> 45 | J138: =Inputs!H35 -> 45 | K138: =Inputs!I35 -> 45 | L138: =Inputs!J35 -> 45 | M138: =Inputs!K35 -> 45 | N138: =Inputs!L35 -> 45 | Q138: =SUM(Model!I134:N134) -> 270 | R138: =SUM(I138:N138) -> 270 | S138: =IF(ISBLANK(Model!I134),0,IF(Q138=R138,1,0)) -> 1
B139: Inventory | D139: (Days) | F139: =(F145/F134)*F$132 -> 23.615554 | G139: =(G145/G134)*G$132 -> 24.689402 | H139: =(H145/H134)*H$132 -> 25.1125 | I139: =Inputs!G36 -> 25 | J139: =Inputs!H36 -> 25 | K139: =Inputs!I36 -> 25 | L139: =Inputs!J36 -> 25 | M139: =Inputs!K36 -> 25 | N139: =Inputs!L36 -> 25 | Q139: =SUM(Model!I135:N135) -> 150 | R139: =SUM(I139:N139) -> 150 | S139: =IF(ISBLANK(Model!I135),0,IF(Q139=R139,1,0)) -> 1
B140: Accounts Payable | D140: (Days) | F140: =(F146/F134)*F$132 -> 39.851247 | G140: =(G146/G134)*G$132 -> 41.149003 | H140: =(H146/H134)*H$132 -> 41.4875 | I140: =Inputs!G37 -> 40 | J140: =Inputs!H37 -> 40 | K140: =Inputs!I37 -> 40 | L140: =Inputs!J37 -> 40 | M140: =Inputs!K37 -> 40 | N140: =Inputs!L37 -> 40 | Q140: =SUM(Model!I136:N136) -> 240 | R140: =SUM(I140:N140) -> 240 | S140: =IF(ISBLANK(Model!I136),0,IF(Q140=R140,1,0)) -> 1
B143: TOTAL AMOUNTS
B144: Accounts Receivable | F144: 5708 | G144: 6333 | H144: 6624 | I144: =(I138/I$132)*I133 -> #REF! | J144: =(J138/J$132)*J133 -> #REF! | K144: =(K138/K$132)*K133 -> #REF! | L144: =(L138/L$132)*L133 -> #REF! | M144: =(M138/M$132)*M133 -> #REF! | N144: =(N138/N$132)*N133 -> #REF!
B145: Inventory | F145: 1792 | G145: 1923 | H145: 2009 | I145: =(I139/I$132)*I134 -> #REF! | J145: =(J139/J$132)*J134 -> #REF! | K145: =(K139/K$132)*K134 -> #REF! | L145: =(L139/L$132)*L134 -> #REF! | M145: =(M139/M$132)*M134 -> #REF! | N145: =(N139/N$132)*N134 -> #REF!
B146: Accounts Payable | F146: 3024 | G146: 3205 | H146: 3319 | I146: =(I140/I$132)*I134 -> #REF! | J146: =(J140/J$132)*J134 -> #REF! | K146: =(K140/K$132)*K134 -> #REF! | L146: =(L140/L$132)*L134 -> #REF! | M146: =(M140/M$132)*M134 -> #REF! | N146: =(N140/N$132)*N134 -> #REF!
B149: NET WORKING CAPITAL
B150: Current Assets | F150: =SUM(F144:F145) -> 7500 | G150: =SUM(G144:G145) -> 8256 | H150: =SUM(H144:H145) -> 8633 | I150: =SUM(I144:I145) -> #REF! | J150: =SUM(J144:J145) -> #REF! | K150: =SUM(K144:K145) -> #REF! | L150: =SUM(L144:L145) -> #REF! | M150: =SUM(M144:M145) -> #REF! | N150: =SUM(N144:N145) -> #REF!
B151: Current Liabilities | F151: =SUM(F146) -> 3024 | G151: =SUM(G146) -> 3205 | H151: =SUM(H146) -> 3319 | I151: =SUM(I146) -> #REF! | J151: =SUM(J146) -> #REF! | K151: =SUM(K146) -> #REF! | L151: =SUM(L146) -> #REF! | M151: =SUM(M146) -> #REF! | N151: =SUM(N146) -> #REF!
B152: Net Working Capital | F152: =F150-F151 -> 4476 | G152: =G150-G151 -> 5051 | H152: =H150-H151 -> 5314 | I152: =I150-I151 -> #REF! | J152: =J150-J151 -> #REF! | K152: =K150-K151 -> #REF! | L152: =L150-L151 -> #REF! | M152: =M150-M151 -> #REF! | N152: =N150-N151 -> #REF!
B155: Cash from Working Capital Items | G155: =F152-G152 -> -575 | H155: =G152-H152 -> -263 | I155: =H152-I152 -> #REF! | J155: =I152-J152 -> #REF! | K155: =J152-K152 -> #REF! | L155: =K152-L152 -> #REF! | M155: =L152-M152 -> #REF! | N155: =M152-N152 -> #REF! | S155: =IF(SUM(S137:S140)=3,"COMPLETE","") -> COMPLETE
N158: We have assumed working capital amounts per day in terminal year are equal to the previous year.
B162: Depreciation Schedule
...
